Workbook

Sheet 新潟マルテーフェア
M2: CODE | AA2: 御 見 積 書
E3: 〒160-8511 | AL3: No. | AN3: FL2503195
D4: 東京都新宿区四谷4-1
AG6: 令和 | AI6: 7 | AL6: 年 | AM6: 3 | AO6: 月 | AP6: 19 | AR6: 日
D7: 大塚刷毛製造株式会社 | T7: 様
D11: 期日 | H11: 2025/4/5-6
D13: 場所 | H13: 新潟マルテーフェア | AB13: 振込先： | AE13: 十六銀行 柳ヶ瀬支店 普通：0777577
D15: 現金支払 | I15: 末締め末現金払い | AB15: 名義： | AE15: ｶ)ﾘﾝｼｭﾝﾄﾞｳ
AB17: 担当者 | AF17: 田中 健吾
J19: =H39 -> 237754
D20: 税込合計 | J20: =H39 -> 237754
B22: 見積書有効期限発効後60日
B24: 品 名 | T24: 数 量 | AA24: 税別単価 | AF24: 金 額 | AM24: 備 考
B26: 展示会 R7/4/5-6 | AF26: =IF(T26="",1*AA26,T26*AA26) -> 0
B27: 交通費 岐阜-新潟 片道 5 時間 41 分（448 km） | X27: 一式 | AA27: 72280 | AF27: =IF(T27="",1*AA27,T27*AA27) -> 72280 | AM27: ETC18,520円
AF28: =IF(T28="",1*AA28,T28*AA28) -> 0
B29: 宿泊費 3泊4日 | X29: 一式 | AA29: 45000 | AF29: =IF(T29="",1*AA29,T29*AA29) -> 45000
B30: 日当 2日分 平日 | X30: 一式 | AA30: 100000 | AF30: =IF(T30="",1*AA30,T30*AA30) -> 100000
B31: 日当 2日分 土日 | X31: 一式 | AA31: 150000 | AF31: =IF(T31="",1*AA31,T31*AA31) -> 150000
B32: 展示会参加デモ用消耗品費 | X32: 一式 | AA32: 15000 | AF32: =IF(T32="",1*AA32,T32*AA32) -> 15000
B33: FL-LCW デモ機追加設置費用 錆び取り専用として | X33: 一式 | AA33: 50000 | AF33: =IF(T33="",1*AA33,T33*AA33) -> 50000
AF34: =IF(T34="",1*AA34,T34*AA34) -> 0
B35: 代理店協力50％値引き | X35: 一式 | AA35: -216140 | AF35: =IF(T35="",1*AA35,T35*AA35) -> -216140
B36: 遮光パネル 溶接用机 ご用意ください。 | AF36: =IF(T36="",1*AA36,T36*AA36) -> 0
B37: デモ機の搬入撤収時男性3名手伝い要します。 | AF37: =IF(T37="",1*AA37,T37*AA37) -> 0
B38: 消費税10% | H38: =AA38*0.1 -> 21614 | T38: 小 計 | AA38: =SUM(AF26:AL37) -> 216140
B39: 合計金額 | H39: =CK115+H38 -> 237754
B40: 摘要：
P56: =SUM(CK115:CQ115) -> 216140
FB100: NO | FC100: 明細NO | FD100: 品名 | FE100: 数量 | FF100: 単位 | FG100: 単位 | FH100: 金額 | FI100: 備考
FB101: 0 | FC101: 1 | FD101: =B26 -> 展示会 R7/4/5-6 | FE101: =T26 -> 0 | FF101: =X26 -> 0 | FG101: =AA26 -> 0 | FH101: =AF26 -> 0 | FI101: =AM26 -> 0
EM102: ON | FB102: 0 | FC102: 2 | FD102: =B27 -> 交通費 岐阜-新潟 片道 5 時間 41 分（448 km） | FE102: =T27 -> 0 | FF102: =X27 -> 一式 | FG102: =AA27 -> 72280 | FH102: =AF27 -> 72280 | FI102: =AM27 -> ETC18,520円
CE103: 制御 | CI103: 総計 | CS103: 単位 | CW103: 消費税 | DD103: タイトル | DM103: ﾏｽﾀﾊﾞｯｸｱｯﾌﾟ | EM103: OFF | FB103: 0 | FC103: 3 | FD103: =B28 -> 0 | FE103: =T28 -> 0 | FF103: =X28 -> 0 | FG103: =AA28 -> 0 | FH103: =AF28 -> 0 | FI103: =AM28 -> 0
CE104: 3 | CI104: 0 | CK104: =AA38 -> 216140 | CS104: 台 | CW104: 5 | CY104: ％ | DD104: 御 見 積 書 | DM104: ON | FB104: 0 | FC104: 4 | FD104: =B29 -> 宿泊費 3泊4日 | FE104: =T29 -> 0 | FF104: =X29 -> 一式 | FG104: =AA29 -> 45000 | FH104: =AF29 -> 45000 | FI104: =AM29 -> 0
CE105: =MAX(FB401:FB642) -> 0 | CI105: 1 | CK105: =IF(ISERROR(#REF!),0,#REF!) -> 0 | CS105: 個 | DD105: 納 品 書 | FB105: 0 | FC105: 5 | FD105: =#REF! -> #REF! | FE105: =T30 -> 0 | FF105: =X30 -> 一式 | FG105: =AA30 -> 100000 | FH105: =AF30 -> 100000 | FI105: =AM30 -> 0
CE106: 1 | CI106: 2 | CK106: =IF(ISERROR(#REF!),0,#REF!) -> 0 | CS106: 一式 | CV106: 画面表示 | DD106: 納 品 書 （控） | DM106: ﾃﾞｰﾀ保存ｼｰﾄ | FB106: 0 | FC106: 6 | FD106: =#REF! -> #REF! | FE106: =T31 -> 0 | FF106: =X31 -> 一式 | FG106: =AA31 -> 150000 | FH106: =AF31 -> 150000 | FI106: =AM31 -> 0
CE107: 0 | CI107: 3 | CK107: =IF(ISERROR(#REF!),0,#REF!) -> 0 | CS107: 冊 | CV107: ① | CW107: 100 | CZ107: ％ | DD107: 請 求 書 | DM107: データ保存 1.xls | FB107: 0 | FC107: 7 | FD107: =#REF! -> #REF! | FE107: =T32 -> 0 | FF107: =X32 -> 一式 | FG107: =AA32 -> 15000 | FH107: =AF32 -> 15000 | FI107: =AM32 -> 0
CE108: 敬称 | CI108: 4 | CS108: 箱 | CV108: ② | CW108: 80 | CZ108: ％ | DD108: 請 求 書 （控） | DM108: 鑑 | FB108: 0 | FC108: 8 | FD108: =B31 -> 日当 2日分 土日 | FE108: =T33 -> 0 | FF108: =X33 -> 一式 | FG108: =AA33 -> 50000 | FH108: =AF33 -> 50000 | FI108: =AM33 -> 0
CE109: 御中 | CI109: 5 | CS109: C/S | DM109: 明細 | FB109: 0 | FC109: 9 | FD109: =B34 -> 0 | FE109: =T34 -> 0 | FF109: =X34 -> 0 | FG109: =AA34 -> 0 | FH109: =AF34 -> 0 | FI109: =AM34 -> 0
CE110: 様 | CI110: 6 | CS110: SET | CV110: 画像ファイル名 | DE110: 画像名 | FB110: 0 | FC110: 10 | FD110: =B35 -> 代理店協力50％値引き | FE110: =T35 -> 0 | FF110: =X35 -> 一式 | FG110: =AA35 -> -216140 | FH110: =AF35 -> -216140 | FI110: =AM35 -> 0
CE111: 殿 | CI111: 7 | CS111: 本 | CV111: ① | CW111: 会社角印.gif | DE111: 会社角印 | FB111: 0 | FC111: 11 | FD111: =B36 -> 遮光パネル 溶接用机 ご用意ください。 | FE111: =T36 -> 0 | FF111: =X36 -> 0 | FG111: =AA36 -> 0 | FH111: =AF36 -> 0 | FI111: =AM36 -> 0
CI112: 8 | CS112: 束 | CV112: ② | CW112: 林印.png | DE112: 林印 | FB112: 0 | FC112: 12 | FD112: =B37 -> デモ機の搬入撤収時男性3名手伝い要します。 | FE112: =T37 -> 0 | FF112: =X37 -> 0 | FG112: =AA37 -> 0 | FH112: =AF37 -> 0 | FI112: =AM37 -> 0
CI113: 9 | CS113: 枚 | CV113: ③ | CW113: 佐藤.png | DE113: 佐藤印 | FB113: 1 | FC113: 1 | FD113: =#REF! -> #REF! | FE113: =#REF! -> #REF! | FF113: =#REF! -> #REF! | FG113: =#REF! -> #REF! | FH113: =#REF! -> #REF! | FI113: =#REF! -> #REF!
CI114: 10 | CS114: ﾊﾟｯｸ | CV114: ④ | CW114: 青木印.gif | DE114: 青木印 | FB114: 1 | FC114: 2 | FD114: =#REF! -> #REF! | FE114: =#REF! -> #REF! | FF114: =#REF! -> #REF! | FG114: =#REF! -> #REF! | FH114: =#REF! -> #REF! | FI114: =#REF! -> #REF!
CI115: 計 | CK115: =SUM(CK104:CQ114) -> 216140 | CS115: ｷｯﾄ | CV115: ⑤ | CW115: 中田印.gif | DE115: 中田印 | FB115: 1 | FC115: 3 | FD115: =#REF! -> #REF! | FE115: =#REF! -> #REF! | FF115: =#REF! -> #REF! | FG115: =#REF! -> #REF! | FH115: =#REF! -> #REF! | FI115: =#REF! -> #REF!
FB116: 1 | FC116: 4 | FD116: =#REF! -> #REF! | FE116: =#REF! -> #REF! | FF116: =#REF! -> #REF! | FG116: =#REF! -> #REF! | FH116: =#REF! -> #REF! | FI116: =#REF! -> #REF!
FB117: 1 | FC117: 5 | FD117: =#REF! -> #REF! | FE117: =#REF! -> #REF! | FF117: =#REF! -> #REF! | FG117: =#REF! -> #REF! | FH117: =#REF! -> #REF! | FI117: =#REF! -> #REF!
FB118: 1 | FC118: 6 | FD118: =#REF! -> #REF! | FE118: =#REF! -> #REF! | FF118: =#REF! -> #REF! | FG118: =#REF! -> #REF! | FH118: =#REF! -> #REF! | FI118: =#REF! -> #REF!
CI119: マスタパス | CM119: C:\Documents and Settings\sato\My Documents\シンプル見積書\ | DM119: ﾏｽﾀ | DO119: マスタ 1.xls | FB119: 1 | FC119: 7 | FD119: =#REF! -> #REF! | FE119: =#REF! -> #REF! | FF119: =#REF! -> #REF! | FG119: =#REF! -> #REF! | FH119: =#REF! -> #REF! | FI119: =#REF! -> #REF!
CI120: データﾊﾟｽ | FB120: 1 | FC120: 8 | FD120: =#REF! -> #REF! | FE120: =#REF! -> #REF! | FF120: =#REF! -> #REF! | FG120: =#REF! -> #REF! | FH120: =#REF! -> #REF! | FI120: =#REF! -> #REF!
FB121: 1 | FC121: 9 | FD121: =#REF! -> #REF! | FE121: =#REF! -> #REF! | FF121: =#REF! -> #REF! | FG121: =#REF! -> #REF! | FH121: =#REF! -> #REF! | FI121: =#REF! -> #REF!
FB122: 1 | FC122: 10 | FD122: =#REF! -> #REF! | FE122: =#REF! -> #REF! | FF122: =#REF! -> #REF! | FG122: =#REF! -> #REF! | FH122: =#REF! -> #REF! | FI122: =#REF! -> #REF!
FB123: 1 | FC123: 11 | FD123: =#REF! -> #REF! | FE123: =#REF! -> #REF! | FF123: =#REF! -> #REF! | FG123: =#REF! -> #REF! | FH123: =#REF! -> #REF! | FI123: =#REF! -> #REF!
FB124: 1 | FC124: 12 | FD124: =#REF! -> #REF! | FE124: =#REF! -> #REF! | FF124: =#REF! -> #REF! | FG124: =#REF! -> #REF! | FH124: =#REF! -> #REF! | FI124: =#REF! -> #REF!
FB125: 1 | FC125: 13 | FD125: =#REF! -> #REF! | FE125: =#REF! -> #REF! | FF125: =#REF! -> #REF! | FG125: =#REF! -> #REF! | FH125: =#REF! -> #REF! | FI125: =#REF! -> #REF!
FB126: 1 | FC126: 14 | FD126: =#REF! -> #REF! | FE126: =#REF! -> #REF! | FF126: =#REF! -> #REF! | FG126: =#REF! -> #REF! | FH126: =#REF! -> #REF! | FI126: =#REF! -> #REF!
FB127: 1 | FC127: 15 | FD127: =#REF! -> #REF! | FE127: =#REF! -> #REF! | FF127: =#REF! -> #REF! | FG127: =#REF! -> #REF! | FH127: =#REF! -> #REF! | FI127: =#REF! -> #REF!
FB128: 1 | FC128: 16 | FD128: =#REF! -> #REF! | FE128: =#REF! -> #REF! | FF128: =#REF! -> #REF! | FG128: =#REF! -> #REF! | FH128: =#REF! -> #REF! | FI128: =#REF! -> #REF!
FB129: 1 | FC129: 17 | FD129: =#REF! -> #REF! | FE129: =#REF! -> #REF! | FF129: =#REF! -> #REF! | FG129: =#REF! -> #REF! | FH129: =#REF! -> #REF! | FI129: =#REF! -> #REF!
FB130: 1 | FC130: 18 | FD130: =#REF! -> #REF! | FE130: =#REF! -> #REF! | FF130: =#REF! -> #REF! | FG130: =#REF! -> #REF! | FH130: =#REF! -> #REF! | FI130: =#REF! -> #REF!
FB131: 1 | FC131: 19 | FD131: =#REF! -> #REF! | FE131: =#REF! -> #REF! | FF131: =#REF! -> #REF! | FG131: =#REF! -> #REF! | FH131: =#REF! -> #REF! | FI131: =#REF! -> #REF!
FB132: 1 | FC132: 20 | FD132: =#REF! -> #REF! | FE132: =#REF! -> #REF! | FF132: =#REF! -> #REF! | FG132: =#REF! -> #REF! | FH132: =#REF! -> #REF! | FI132: =#REF! -> #REF!
... FB173: 3 | FC173: 15 | FD173: =#REF! -> #REF! | FE173: =#REF! -> #REF! | FF173: =#REF! -> #REF! | FG173: =#REF! -> #REF! | FH173: =#REF! -> #REF! | FI173: =#REF! -> #REF!
P174: 0 | Q174: 15 | R174: 32 | S174: 117 | T174: 41 | U174: 124 | FB174: 3 | FC174: 16 | FD174: =#REF! -> #REF! | FE174: =#REF! -> #REF! | FF174: =#REF! -> #REF! | FG174: =#REF! -> #REF! | FH174: =#REF! -> #REF! | FI174: =#REF! -> #REF!
FB175: 3 | FC175: 17 | FD175: =#REF! -> #REF! | FE175: =#REF! -> #REF! | FF175: =#REF! -> #REF! | FG175: =#REF! -> #REF! | FH175: =#REF! -> #REF! | FI175: =#REF! -> #REF!
P176: 00-F-20-75-29-7C | FB176: 3 | FC176: 18 | FD176: =#REF! -> #REF! | FE176: =#REF! -> #REF! | FF176: =#REF! -> #REF! | FG176: =#REF! -> #REF! | FH176: =#REF! -> #REF! | FI176: =#REF! -> #REF!
FB177: 3 | FC177: 19 | FD177: =#REF! -> #REF! | FE177: =#REF! -> #REF! | FF177: =#REF! -> #REF! | FG177: =#REF! -> #REF! | FH177: =#REF! -> #REF! | FI177: =#REF! -> #REF!
FB178: 3 | FC178: 20 | FD178: =#REF! -> #REF! | FE178: =#REF! -> #REF! | FF178: =#REF! -> #REF! | FG178: =#REF! -> #REF! | FH178: =#REF! -> #REF! | FI178: =#REF! -> #REF!
FB179: 3 | FC179: 21 | FD179: =#REF! -> #REF! | FE179: =#REF! -> #REF! | FF179: =#REF! -> #REF! | FG179: =#REF! -> #REF! | FH179: =#REF! -> #REF! | FI179: =#REF! -> #REF!
FB180: 3 | FC180: 22 | FD180: =#REF! -> #REF! | FE180: =#REF! -> #REF! | FF180: =#REF! -> #REF! | FG180: =#REF! -> #REF! | FH180: =#REF! -> #REF! | FI180: =#REF! -> #REF!
FB181: 3 | FC181: 23 | FD181: =#REF! -> #REF! | FE181: =#REF! -> #REF! | FF181: =#REF! -> #REF! | FG181: =#REF! -> #REF! | FH181: =#REF! -> #REF! | FI181: =#REF! -> #REF!
FB400: NO | FC400: 明細NO | FD400: 品名 | FE400: 数量 | FF400: 単位 | FG400: 単価 | FH400: 金額 | FI400: 備考

Sheet オートビジネス2025
M2: CODE | AA2: 御 見 積 書
E3: 〒922-0857 | AL3: No. | AN3: FL2505085
D4: 石川県加賀市永井町89
F6: 北陸営業所 | AG6: 令和 | AI6: 7 | AL6: 年 | AM6: 5 | AO6: 月 | AP6: 8 | AR6: 日
D7: 大塚刷毛製造株式会社 | T7: 様
D11: 期日 | H11: 2025/9/5-6
D13: 場所 | H13: オートビジネスフェアKYOTO2025 | AB13: 振込先： | AE13: 十六銀行 柳ヶ瀬支店 普通：0777577
D15: 現金支払 | I15: 末締め末現金払い | AB15: 名義： | AE15: ｶ)ﾘﾝｼｭﾝﾄﾞｳ
AB17: 担当者 | AF17: 田中 健吾
J19: =H39 -> 129668
D20: 税込合計 | J20: =H39 -> 129668
B22: 見積書有効期限発効後60日
B24: 品 名 | T24: 数 量 | AA24: 税別単価 | AF24: 金 額 | AM24: 備 考
B26: 展示会参加諸経費 | AF26: =IF(T26="",1*AA26,T26*AA26) -> 0
B27: 交通費 岐阜-新潟 片道 2 時間 12 分（154 km） | T27: 1 | X27: 台 | AA27: 18480 | AF27: =IF(T27="",1*AA27,T27*AA27) -> 18480 | AM27: 10k＝600円
B28: ETC利用料金 | T28: 1 | X28: 台 | AA28: 7280 | AF28: =IF(T28="",1*AA28,T28*AA28) -> 7280
B29: 宿泊費 1泊2日 1名分 | X29: 一式 | AA29: 15000 | AF29: =IF(T29="",1*AA29,T29*AA29) -> 15000
B30: 日当１日分 平日 | X30: 一式 | AA30: 50000 | AF30: =IF(T30="",1*AA30,T30*AA30) -> 50000
B31: 日当１日分 土日 | X31: 一式 | AA31: 75000 | AF31: =IF(T31="",1*AA31,T31*AA31) -> 75000
B32: 展示会参加デモ用消耗品費 | X32: 一式 | AA32: 17500 | AF32: =IF(T32="",1*AA32,T32*AA32) -> 17500
B33: FL-LCW デモ機追加設置費用LCW1.5kw錆び取り | X33: 一式 | AA33: 50000 | AF33: =IF(T33="",1*AA33,T33*AA33) -> 50000
AF34: =IF(T34="",1*AA34,T34*AA34) -> 0
B35: 代理店協力50％値引き | X35: 一式 | AA35: -115380 | AF35: =IF(T35="",1*AA35,T35*AA35) -> -115380
B36: 遮光パネル付き溶接台準備します。 | AF36: =IF(T36="",1*AA36,T36*AA36) -> 0
B37: デモ機の搬入撤収時男性3名手伝い要します。 | AF37: =IF(T37="",1*AA37,T37*AA37) -> 0
B38: 消費税10% | H38: =AA38*0.1 -> 11788 | T38: 小 計 | AA38: =SUM(AF26:AL37) -> 117880
B39: 合計金額 | H39: =CK115+H38 -> 129668
B40: 摘要：
P56: =SUM(CK115:CQ115) -> 117880
FB100: NO | FC100: 明細NO | FD100: 品名 | FE100: 数量 | FF100: 単位 | FG100: 単位 | FH100: 金額 | FI100: 備考
FB101: 0 | FC101: 1 | FD101: =B26 -> 展示会参加諸経費 | FE101: =T26 -> 0 | FF101: =X26 -> 0 | FG101: =AA26 -> 0 | FH101: =AF26 -> 0 | FI101: =AM26 -> 0
EM102: ON | FB102: 0 | FC102: 2 | FD102: =B27 -> 交通費 岐阜-新潟 片道 2 時間 12 分（154 km） | FE102: =T27 -> 1 | FF102: =X27 -> 台 | FG102: =AA27 -> 18480 | FH102: =AF27 -> 18480 | FI102: =AM27 -> 10k＝600円
CE103: 制御 | CI103: 総計 | CS103: 単位 | CW103: 消費税 | DD103: タイトル | DM103: ﾏｽﾀﾊﾞｯｸｱｯﾌﾟ | EM103: OFF | FB103: 0 | FC103: 3 | FD103: =B28 -> ETC利用料金 | FE103: =T28 -> 1 | FF103: =X28 -> 台 | FG103: =AA28 -> 7280 | FH103: =AF28 -> 7280 | FI103: =AM28 -> 0
CE104: 3 | CI104: 0 | CK104: =AA38 -> 117880 | CS104: 台 | CW104: 5 | CY104: ％ | DD104: 御 見 積 書 | DM104: ON | FB104: 0 | FC104: 4 | FD104: =B29 -> 宿泊費 1泊2日 1名分 | FE104: =T29 -> 0 | FF104: =X29 -> 一式 | FG104: =AA29 -> 15000 | FH104: =AF29 -> 15000 | FI104: =AM29 -> 0
CE105: =MAX(FB401:FB642) -> 0 | CI105: 1 | CK105: =IF(ISERROR(#REF!),0,#REF!) -> 0 | CS105: 個 | DD105: 納 品 書 | FB105: 0 | FC105: 5 | FD105: =#REF! -> #REF! | FE105: =T30 -> 0 | FF105: =X30 -> 一式 | FG105: =AA30 -> 50000 | FH105: =AF30 -> 50000 | FI105: =AM30 -> 0
CE106: 1 | CI106: 2 | CK106: =IF(ISERROR(#REF!),0,#REF!) -> 0 | CS106: 一式 | CV106: 画面表示 | DD106: 納 品 書 （控） | DM106: ﾃﾞｰﾀ保存ｼｰﾄ | FB106: 0 | FC106: 6 | FD106: =#REF! -> #REF! | FE106: =T31 -> 0 | FF106: =X31 -> 一式 | FG106: =AA31 -> 75000 | FH106: =AF31 -> 75000 | FI106: =AM31 -> 0
CE107: 0 | CI107: 3 | CK107: =IF(ISERROR(#REF!),0,#REF!) -> 0 | CS107: 冊 | CV107: ① | CW107: 100 | CZ107: ％ | DD107: 請 求 書 | DM107: データ保存 1.xls | FB107: 0 | FC107: 7 | FD107: =#REF! -> #REF! | FE107: =T32 -> 0 | FF107: =X32 -> 一式 | FG107: =AA32 -> 17500 | FH107: =AF32 -> 17500 | FI107: =AM32 -> 0
CE108: 敬称 | CI108: 4 | CS108: 箱 | CV108: ② | CW108: 80 | CZ108: ％ | DD108: 請 求 書 （控） | DM108: 鑑 | FB108: 0 | FC108: 8 | FD108: =B31 -> 日当１日分 土日 | FE108: =T33 -> 0 | FF108: =X33 -> 一式 | FG108: =AA33 -> 50000 | FH108: =AF33 -> 50000 | FI108: =AM33 -> 0
CE109: 御中 | CI109: 5 | CS109: C/S | DM109: 明細 | FB109: 0 | FC109: 9 | FD109: =B34 -> 0 | FE109: =T34 -> 0 | FF109: =X34 -> 0 | FG109: =AA34 -> 0 | FH109: =AF34 -> 0 | FI109: =AM34 -> 0
CE110: 様 | CI110: 6 | CS110: SET | CV110: 画像ファイル名 | DE110: 画像名 | FB110: 0 | FC110: 10 | FD110: =B35 -> 代理店協力50％値引き | FE110: =T35 -> 0 | FF110: =X35 -> 一式 | FG110: =AA35 -> -115380 | FH110: =AF35 -> -115380 | FI110: =AM35 -> 0
CE111: 殿 | CI111: 7 | CS111: 本 | CV111: ① | CW111: 会社角印.gif | DE111: 会社角印 | FB111: 0 | FC111: 11 | FD111: =B36 -> 遮光パネル付き溶接台準備します。 | FE111: =T36 -> 0 | FF111: =X36 -> 0 | FG111: =AA36 -> 0 | FH111: =AF36 -> 0 | FI111: =AM36 -> 0
CI112: 8 | CS112: 束 | CV112: ② | CW112: 林印.png | DE112: 林印 | FB112: 0 | FC112: 12 | FD112: =B37 -> デモ機の搬入撤収時男性3名手伝い要します。 | FE112: =T37 -> 0 | FF112: =X37 -> 0 | FG112: =AA37 -> 0 | FH112: =AF37 -> 0 | FI112: =AM37 -> 0
CI113: 9 | CS113: 枚 | CV113: ③ | CW113: 佐藤.png | DE113: 佐藤印 | FB113: 1 | FC113: 1 | FD113: =#REF! -> #REF! | FE113: =#REF! -> #REF! | FF113: =#REF! -> #REF! | FG113: =#REF! -> #REF! | FH113: =#REF! -> #REF! | FI113: =#REF! -> #REF!
CI114: 10 | CS114: ﾊﾟｯｸ | CV114: ④ | CW114: 青木印.gif | DE114: 青木印 | FB114: 1 | FC114: 2 | FD114: =#REF! -> #REF! | FE114: =#REF! -> #REF! | FF114: =#REF! -> #REF! | FG114: =#REF! -> #REF! | FH114: =#REF! -> #REF! | FI114: =#REF! -> #REF!
CI115: 計 | CK115: =SUM(CK104:CQ114) -> 117880 | CS115: ｷｯﾄ | CV115: ⑤ | CW115: 中田印.gif | DE115: 中田印 | FB115: 1 | FC115: 3 | FD115: =#REF! -> #REF! | FE115: =#REF! -> #REF! | FF115: =#REF! -> #REF! | FG115: =#REF! -> #REF! | FH115: =#REF! -> #REF! | FI115: =#REF! -> #REF!
FB116: 1 | FC116: 4 | FD116: =#REF! -> #REF! | FE116: =#REF! -> #REF! | FF116: =#REF! -> #REF! | FG116: =#REF! -> #REF! | FH116: =#REF! -> #REF! | FI116: =#REF! -> #REF!
FB117: 1 | FC117: 5 | FD117: =#REF! -> #REF! | FE117: =#REF! -> #REF! | FF117: =#REF! -> #REF! | FG117: =#REF! -> #REF! | FH117: =#REF! -> #REF! | FI117: =#REF! -> #REF!
FB118: 1 | FC118: 6 | FD118: =#REF! -> #REF! | FE118: =#REF! -> #REF! | FF118: =#REF! -> #REF! | FG118: =#REF! -> #REF! | FH118: =#REF! -> #REF! | FI118: =#REF! -> #REF!
CI119: マスタパス | CM119: C:\Documents and Settings\sato\My Documents\シンプル見積書\ | DM119: ﾏｽﾀ | DO119: マスタ 1.xls | FB119: 1 | FC119: 7 | FD119: =#REF! -> #REF! | FE119: =#REF! -> #REF! | FF119: =#REF! -> #REF! | FG119: =#REF! -> #REF! | FH119: =#REF! -> #REF! | FI119: =#REF! -> #REF!
CI120: データﾊﾟｽ | FB120: 1 | FC120: 8 | FD120: =#REF! -> #REF! | FE120: =#REF! -> #REF! | FF120: =#REF! -> #REF! | FG120: =#REF! -> #REF! | FH120: =#REF! -> #REF! | FI120: =#REF! -> #REF!
FB121: 1 | FC121: 9 | FD121: =#REF! -> #REF! | FE121: =#REF! -> #REF! | FF121: =#REF! -> #REF! | FG121: =#REF! -> #REF! | FH121: =#REF! -> #REF! | FI121: =#REF! -> #REF!
FB122: 1 | FC122: 10 | FD122: =#REF! -> #REF! | FE122: =#REF! -> #REF! | FF122: =#REF! -> #REF! | FG122: =#REF! -> #REF! | FH122: =#REF! -> #REF! | FI122: =#REF! -> #REF!
FB123: 1 | FC123: 11 | FD123: =#REF! -> #REF! | FE123: =#REF! -> #REF! | FF123: =#REF! -> #REF! | FG123: =#REF! -> #REF! | FH123: =#REF! -> #REF! | FI123: =#REF! -> #REF!
FB124: 1 | FC124: 12 | FD124: =#REF! -> #REF! | FE124: =#REF! -> #REF! | FF124: =#REF! -> #REF! | FG124: =#REF! -> #REF! | FH124: =#REF! -> #REF! | FI124: =#REF! -> #REF!
FB125: 1 | FC125: 13 | FD125: =#REF! -> #REF! | FE125: =#REF! -> #REF! | FF125: =#REF! -> #REF! | FG125: =#REF! -> #REF! | FH125: =#REF! -> #REF! | FI125: =#REF! -> #REF!
FB126: 1 | FC126: 14 | FD126: =#REF! -> #REF! | FE126: =#REF! -> #REF! | FF126: =#REF! -> #REF! | FG126: =#REF! -> #REF! | FH126: =#REF! -> #REF! | FI126: =#REF! -> #REF!
FB127: 1 | FC127: 15 | FD127: =#REF! -> #REF! | FE127: =#REF! -> #REF! | FF127: =#REF! -> #REF! | FG127: =#REF! -> #REF! | FH127: =#REF! -> #REF! | FI127: =#REF! -> #REF!
FB128: 1 | FC128: 16 | FD128: =#REF! -> #REF! | FE128: =#REF! -> #REF! | FF128: =#REF! -> #REF! | FG128: =#REF! -> #REF! | FH128: =#REF! -> #REF! | FI128: =#REF! -> #REF!
FB129: 1 | FC129: 17 | FD129: =#REF! -> #REF! | FE129: =#REF! -> #REF! | FF129: =#REF! -> #REF! | FG129: =#REF! -> #REF! | FH129: =#REF! -> #REF! | FI129: =#REF! -> #REF!
FB130: 1 | FC130: 18 | FD130: =#REF! -> #REF! | FE130: =#REF! -> #REF! | FF130: =#REF! -> #REF! | FG130: =#REF! -> #REF! | FH130: =#REF! -> #REF! | FI130: =#REF! -> #REF!
FB131: 1 | FC131: 19 | FD131: =#REF! -> #REF! | FE131: =#REF! -> #REF! | FF131: =#REF! -> #REF! | FG131: =#REF! -> #REF! | FH131: =#REF! -> #REF! | FI131: =#REF! -> #REF!
FB132: 1 | FC132: 20 | FD132: =#REF! -> #REF! | FE132: =#REF! -> #REF! | FF132: =#REF! -> #REF! | FG132: =#REF! -> #REF! | FH132: =#REF! -> #REF! | FI132: =#REF! -> #REF!
... FB173: 3 | FC173: 15 | FD173: =#REF! -> #REF! | FE173: =#REF! -> #REF! | FF173: =#REF! -> #REF! | FG173: =#REF! -> #REF! | FH173: =#REF! -> #REF! | FI173: =#REF! -> #REF!
P174: 0 | Q174: 15 | R174: 32 | S174: 117 | T174: 41 | U174: 124 | FB174: 3 | FC174: 16 | FD174: =#REF! -> #REF! | FE174: =#REF! -> #REF! | FF174: =#REF! -> #REF! | FG174: =#REF! -> #REF! | FH174: =#REF! -> #REF! | FI174: =#REF! -> #REF!
FB175: 3 | FC175: 17 | FD175: =#REF! -> #REF! | FE175: =#REF! -> #REF! | FF175: =#REF! -> #REF! | FG175: =#REF! -> #REF! | FH175: =#REF! -> #REF! | FI175: =#REF! -> #REF!
P176: 00-F-20-75-29-7C | FB176: 3 | FC176: 18 | FD176: =#REF! -> #REF! | FE176: =#REF! -> #REF! | FF176: =#REF! -> #REF! | FG176: =#REF! -> #REF! | FH176: =#REF! -> #REF! | FI176: =#REF! -> #REF!
FB177: 3 | FC177: 19 | FD177: =#REF! -> #REF! | FE177: =#REF! -> #REF! | FF177: =#REF! -> #REF! | FG177: =#REF! -> #REF! | FH177: =#REF! -> #REF! | FI177: =#REF! -> #REF!
FB178: 3 | FC178: 20 | FD178: =#REF! -> #REF! | FE178: =#REF! -> #REF! | FF178: =#REF! -> #REF! | FG178: =#REF! -> #REF! | FH178: =#REF! -> #REF! | FI178: =#REF! -> #REF!
FB179: 3 | FC179: 21 | FD179: =#REF! -> #REF! | FE179: =#REF! -> #REF! | FF179: =#REF! -> #REF! | FG179: =#REF! -> #REF! | FH179: =#REF! -> #REF! | FI179: =#REF! -> #REF!
FB180: 3 | FC180: 22 | FD180: =#REF! -> #REF! | FE180: =#REF! -> #REF! | FF180: =#REF! -> #REF! | FG180: =#REF! -> #REF! | FH180: =#REF! -> #REF! | FI180: =#REF! -> #REF!
FB181: 3 | FC181: 23 | FD181: =#REF! -> #REF! | FE181: =#REF! -> #REF! | FF181: =#REF! -> #REF! | FG181: =#REF! -> #REF! | FH181: =#REF! -> #REF! | FI181: =#REF! -> #REF!
FB400: NO | FC400: 明細NO | FD400: 品名 | FE400: 数量 | FF400: 単位 | FG400: 単価 | FH400: 金額 | FI400: 備考

Sheet 群馬フジペックスフェア
M2: CODE | AA2: 御 見 積 書
E3: 〒160-8511 | AL3: No. | AN3: FL2507186
D4: 東京都新宿区四谷4-1
AG6: 令和 | AI6: 7 | AL6: 年 | AM6: 7 | AO6: 月 | AP6: 18 | AR6: 日
D7: 大塚刷毛製造株式会社 | T7: 様
D11: 期日 | H11: 2025/9/6-7
D13: 場所 | H13: 群馬県太田市吉沢町1058-5 | AB13: 振込先： | AE13: 十六銀行 柳ヶ瀬支店 普通：0777577
D15: 現金支払 | I15: 末締め末現金払い | AB15: 名義： | AE15: ｶ)ﾘﾝｼｭﾝﾄﾞｳ
AB17: 担当者 | AF17: 田中 健吾
J19: =H39 -> 220000
D20: 税込合計 | J20: =H39 -> 220000
B24: 品 名 | T24: 数 量 | AA24: 税別単価 | AF24: 金 額 | AM24: 備 考
B26: 展示会参加諸経費 9/6土曜 9/7日曜 | AF26: =IF(T26="",1*AA26,T26*AA26) -> 0
B27: 交通費 往復 岐阜-太田市 商用車使用 | X27: 一式 | AA27: 50000 | AF27: =IF(T27="",1*AA27,T27*AA27) -> 50000
B28: ETC利用料金 | X28: 一式 | AA28: 19400 | AF28: =IF(T28="",1*AA28,T28*AA28) -> 19400
B29: 宿泊費 1泊2日 2名分 | X29: 一式 | AA29: 30000 | AF29: =IF(T29="",1*AA29,T29*AA29) -> 30000
B30: 日当１日1名分 土日 | T30: 4 | X30: 一式 | AA30: 75000 | AF30: =IF(T30="",1*AA30,T30*AA30) -> 300000
B31: FL-LCW デモ機展示設置費用LCW1.5kw | X31: 一式 | AA31: 20000 | AF31: =IF(T31="",1*AA31,T31*AA31) -> 20000
B32: 展示会参加デモ用消耗品費 | X32: 一式 | AA32: 15000 | AF32: =IF(T32="",1*AA32,T32*AA32) -> 15000
B33: 保護メガネ５人分程度、手袋、溶接台 弊社手配 | X33: 一式 | AA33: 10000 | AF33: =IF(T33="",1*AA33,T33*AA33) -> 10000
B34: 追加値引き | X34: 一式 | AA34: -22200 | AF34: =IF(T34="",1*AA34,T34*AA34) -> -22200
B35: 出展協力50％値引き | X35: 一式 | AA35: -222200 | AF35: =IF(T35="",1*AA35,T35*AA35) -> -222200
B36: 電源 遮光パネル 窒素 御社手配 | AF36: =IF(T36="",1*AA36,T36*AA36) -> 0
B37: デモ機の搬入撤収時男性お手伝い要します。 | AF37: =IF(T37="",1*AA37,T37*AA37) -> 0
B38: 消費税10% | H38: =AA38*0.1 -> 20000 | T38: 小 計 | AA38: =SUM(AF26:AL37) -> 200000
B39: 合計金額 | H39: =CK115+H38 -> 220000
B40: 摘要： | E40: 発注書No2489059
B41: 太田市産業支援センター 〒373-0019群馬県太田市吉沢町1058-5
P56: =SUM(CK115:CQ115) -> 200000
FB100: NO | FC100: 明細NO | FD100: 品名 | FE100: 数量 | FF100: 単位 | FG100: 単位 | FH100: 金額 | FI100: 備考
FB101: 0 | FC101: 1 | FD101: =B26 -> 展示会参加諸経費 9/6土曜 9/7日曜 | FE101: =T26 -> 0 | FF101: =X26 -> 0 | FG101: =AA26 -> 0 | FH101: =AF26 -> 0 | FI101: =AM26 -> 0
EM102: ON | FB102: 0 | FC102: 2 | FD102: =B27 -> 交通費 往復 岐阜-太田市 商用車使用 | FE102: =T27 -> 0 | FF102: =X27 -> 一式 | FG102: =AA27 -> 50000 | FH102: =AF27 -> 50000 | FI102: =AM27 -> 0
CE103: 制御 | CI103: 総計 | CS103: 単位 | CW103: 消費税 | DD103: タイトル | DM103: ﾏｽﾀﾊﾞｯｸｱｯﾌﾟ | EM103: OFF | FB103: 0 | FC103: 3 | FD103: =B28 -> ETC利用料金 | FE103: =T28 -> 0 | FF103: =X28 -> 一式 | FG103: =AA28 -> 19400 | FH103: =AF28 -> 19400 | FI103: =AM28 -> 0
CE104: 3 | CI104: 0 | CK104: =AA38 -> 200000 | CS104: 台 | CW104: 5 | CY104: ％ | DD104: 御 見 積 書 | DM104: ON | FB104: 0 | FC104: 4 | FD104: =B29 -> 宿泊費 1泊2日 2名分 | FE104: =T29 -> 0 | FF104: =X29 -> 一式 | FG104: =AA29 -> 30000 | FH104: =AF29 -> 30000 | FI104: =AM29 -> 0
CE105: =MAX(FB401:FB642) -> 0 | CI105: 1 | CK105: =IF(ISERROR(#REF!),0,#REF!) -> 0 | CS105: 個 | DD105: 納 品 書 | FB105: 0 | FC105: 5 | FD105: =#REF! -> #REF! | FE105: =T30 -> 4 | FF105: =X30 -> 一式 | FG105: =AA30 -> 75000 | FH105: =AF30 -> 300000 | FI105: =AM30 -> 0
CE106: 1 | CI106: 2 | CK106: =IF(ISERROR(#REF!),0,#REF!) -> 0 | CS106: 一式 | CV106: 画面表示 | DD106: 納 品 書 （控） | DM106: ﾃﾞｰﾀ保存ｼｰﾄ | FB106: 0 | FC106: 6 | FD106: =#REF! -> #REF! | FE106: =T31 -> 0 | FF106: =X31 -> 一式 | FG106: =AA31 -> 20000 | FH106: =AF31 -> 20000 | FI106: =AM31 -> 0
CE107: 0 | CI107: 3 | CK107: =IF(ISERROR(#REF!),0,#REF!) -> 0 | CS107: 冊 | CV107: ① | CW107: 100 | CZ107: ％ | DD107: 請 求 書 | DM107: データ保存 1.xls | FB107: 0 | FC107: 7 | FD107: =#REF! -> #REF! | FE107: =T32 -> 0 | FF107: =X32 -> 一式 | FG107: =AA32 -> 15000 | FH107: =AF32 -> 15000 | FI107: =AM32 -> 0
CE108: 敬称 | CI108: 4 | CS108: 箱 | CV108: ② | CW108: 80 | CZ108: ％ | DD108: 請 求 書 （控） | DM108: 鑑 | FB108: 0 | FC108: 8 | FD108: =B31 -> FL-LCW デモ機展示設置費用LCW1.5kw | FE108: =T33 -> 0 | FF108: =X33 -> 一式 | FG108: =AA33 -> 10000 | FH108: =AF33 -> 10000 | FI108: =AM33 -> 0
CE109: 御中 | CI109: 5 | CS109: C/S | DM109: 明細 | FB109: 0 | FC109: 9 | FD109: =B34 -> 追加値引き | FE109: =T34 -> 0 | FF109: =X34 -> 一式 | FG109: =AA34 -> -22200 | FH109: =AF34 -> -22200 | FI109: =AM34 -> 0
CE110: 様 | CI110: 6 | CS110: SET | CV110: 画像ファイル名 | DE110: 画像名 | FB110: 0 | FC110: 10 | FD110: =B35 -> 出展協力50％値引き | FE110: =T35 -> 0 | FF110: =X35 -> 一式 | FG110: =AA35 -> -222200 | FH110: =AF35 -> -222200 | FI110: =AM35 -> 0
CE111: 殿 | CI111: 7 | CS111: 本 | CV111: ① | CW111: 会社角印.gif | DE111: 会社角印 | FB111: 0 | FC111: 11 | FD111: =B36 -> 電源 遮光パネル 窒素 御社手配 | FE111: =T36 -> 0 | FF111: =X36 -> 0 | FG111: =AA36 -> 0 | FH111: =AF36 -> 0 | FI111: =AM36 -> 0
CI112: 8 | CS112: 束 | CV112: ② | CW112: 林印.png | DE112: 林印 | FB112: 0 | FC112: 12 | FD112: =B37 -> デモ機の搬入撤収時男性お手伝い要します。 | FE112: =T37 -> 0 | FF112: =X37 -> 0 | FG112: =AA37 -> 0 | FH112: =AF37 -> 0 | FI112: =AM37 -> 0
CI113: 9 | CS113: 枚 | CV113: ③ | CW113: 佐藤.png | DE113: 佐藤印 | FB113: 1 | FC113: 1 | FD113: =#REF! -> #REF! | FE113: =#REF! -> #REF! | FF113: =#REF! -> #REF! | FG113: =#REF! -> #REF! | FH113: =#REF! -> #REF! | FI113: =#REF! -> #REF!
CI114: 10 | CS114: ﾊﾟｯｸ | CV114: ④ | CW114: 青木印.gif | DE114: 青木印 | FB114: 1 | FC114: 2 | FD114: =#REF! -> #REF! | FE114: =#REF! -> #REF! | FF114: =#REF! -> #REF! | FG114: =#REF! -> #REF! | FH114: =#REF! -> #REF! | FI114: =#REF! -> #REF!
CI115: 計 | CK115: =SUM(CK104:CQ114) -> 200000 | CS115: ｷｯﾄ | CV115: ⑤ | CW115: 中田印.gif | DE115: 中田印 | FB115: 1 | FC115: 3 | FD115: =#REF! -> #REF! | FE115: =#REF! -> #REF! | FF115: =#REF! -> #REF! | FG115: =#REF! -> #REF! | FH115: =#REF! -> #REF! | FI115: =#REF! -> #REF!
FB116: 1 | FC116: 4 | FD116: =#REF! -> #REF! | FE116: =#REF! -> #REF! | FF116: =#REF! -> #REF! | FG116: =#REF! -> #REF! | FH116: =#REF! -> #REF! | FI116: =#REF! -> #REF!
FB117: 1 | FC117: 5 | FD117: =#REF! -> #REF! | FE117: =#REF! -> #REF! | FF117: =#REF! -> #REF! | FG117: =#REF! -> #REF! | FH117: =#REF! -> #REF! | FI117: =#REF! -> #REF!
FB118: 1 | FC118: 6 | FD118: =#REF! -> #REF! | FE118: =#REF! -> #REF! | FF118: =#REF! -> #REF! | FG118: =#REF! -> #REF! | FH118: =#REF! -> #REF! | FI118: =#REF! -> #REF!
CI119: マスタパス | CM119: C:\Documents and Settings\sato\My Documents\シンプル見積書\ | DM119: ﾏｽﾀ | DO119: マスタ 1.xls | FB119: 1 | FC119: 7 | FD119: =#REF! -> #REF! | FE119: =#REF! -> #REF! | FF119: =#REF! -> #REF! | FG119: =#REF! -> #REF! | FH119: =#REF! -> #REF! | FI119: =#REF! -> #REF!
CI120: データﾊﾟｽ | FB120: 1 | FC120: 8 | FD120: =#REF! -> #REF! | FE120: =#REF! -> #REF! | FF120: =#REF! -> #REF! | FG120: =#REF! -> #REF! | FH120: =#REF! -> #REF! | FI120: =#REF! -> #REF!
FB121: 1 | FC121: 9 | FD121: =#REF! -> #REF! | FE121: =#REF! -> #REF! | FF121: =#REF! -> #REF! | FG121: =#REF! -> #REF! | FH121: =#REF! -> #REF! | FI121: =#REF! -> #REF!
FB122: 1 | FC122: 10 | FD122: =#REF! -> #REF! | FE122: =#REF! -> #REF! | FF122: =#REF! -> #REF! | FG122: =#REF! -> #REF! | FH122: =#REF! -> #REF! | FI122: =#REF! -> #REF!
FB123: 1 | FC123: 11 | FD123: =#REF! -> #REF! | FE123: =#REF! -> #REF! | FF123: =#REF! -> #REF! | FG123: =#REF! -> #REF! | FH123: =#REF! -> #REF! | FI123: =#REF! -> #REF!
FB124: 1 | FC124: 12 | FD124: =#REF! -> #REF! | FE124: =#REF! -> #REF! | FF124: =#REF! -> #REF! | FG124: =#REF! -> #REF! | FH124: =#REF! -> #REF! | FI124: =#REF! -> #REF!
FB125: 1 | FC125: 13 | FD125: =#REF! -> #REF! | FE125: =#REF! -> #REF! | FF125: =#REF! -> #REF! | FG125: =#REF! -> #REF! | FH125: =#REF! -> #REF! | FI125: =#REF! -> #REF!
FB126: 1 | FC126: 14 | FD126: =#REF! -> #REF! | FE126: =#REF! -> #REF! | FF126: =#REF! -> #REF! | FG126: =#REF! -> #REF! | FH126: =#REF! -> #REF! | FI126: =#REF! -> #REF!
FB127: 1 | FC127: 15 | FD127: =#REF! -> #REF! | FE127: =#REF! -> #REF! | FF127: =#REF! -> #REF! | FG127: =#REF! -> #REF! | FH127: =#REF! -> #REF! | FI127: =#REF! -> #REF!
FB128: 1 | FC128: 16 | FD128: =#REF! -> #REF! | FE128: =#REF! -> #REF! | FF128: =#REF! -> #REF! | FG128: =#REF! -> #REF! | FH128: =#REF! -> #REF! | FI128: =#REF! -> #REF!
FB129: 1 | FC129: 17 | FD129: =#REF! -> #REF! | FE129: =#REF! -> #REF! | FF129: =#REF! -> #REF! | FG129: =#REF! -> #REF! | FH129: =#REF! -> #REF! | FI129: =#REF! -> #REF!
FB130: 1 | FC130: 18 | FD130: =#REF! -> #REF! | FE130: =#REF! -> #REF! | FF130: =#REF! -> #REF! | FG130: =#REF! -> #REF! | FH130: =#REF! -> #REF! | FI130: =#REF! -> #REF!
FB131: 1 | FC131: 19 | FD131: =#REF! -> #REF! | FE131: =#REF! -> #REF! | FF131: =#REF! -> #REF! | FG131: =#REF! -> #REF! | FH131: =#REF! -> #REF! | FI131: =#REF! -> #REF!
FB132: 1 | FC132: 20 | FD132: =#REF! -> #REF! | FE132: =#REF! -> #REF! | FF132: =#REF! -> #REF! | FG132: =#REF! -> #REF! | FH132: =#REF! -> #REF! | FI132: =#REF! -> #REF!
... FB173: 3 | FC173: 15 | FD173: =#REF! -> #REF! | FE173: =#REF! -> #REF! | FF173: =#REF! -> #REF! | FG173: =#REF! -> #REF! | FH173: =#REF! -> #REF! | FI173: =#REF! -> #REF!
P174: 0 | Q174: 15 | R174: 32 | S174: 117 | T174: 41 | U174: 124 | FB174: 3 | FC174: 16 | FD174: =#REF! -> #REF! | FE174: =#REF! -> #REF! | FF174: =#REF! -> #REF! | FG174: =#REF! -> #REF! | FH174: =#REF! -> #REF! | FI174: =#REF! -> #REF!
FB175: 3 | FC175: 17 | FD175: =#REF! -> #REF! | FE175: =#REF! -> #REF! | FF175: =#REF! -> #REF! | FG175: =#REF! -> #REF! | FH175: =#REF! -> #REF! | FI175: =#REF! -> #REF!
P176: 00-F-20-75-29-7C | FB176: 3 | FC176: 18 | FD176: =#REF! -> #REF! | FE176: =#REF! -> #REF! | FF176: =#REF! -> #REF! | FG176: =#REF! -> #REF! | FH176: =#REF! -> #REF! | FI176: =#REF! -> #REF!
FB177: 3 | FC177: 19 | FD177: =#REF! -> #REF! | FE177: =#REF! -> #REF! | FF177: =#REF! -> #REF! | FG177: =#REF! -> #REF! | FH177: =#REF! -> #REF! | FI177: =#REF! -> #REF!
FB178: 3 | FC178: 20 | FD178: =#REF! -> #REF! | FE178: =#REF! -> #REF! | FF178: =#REF! -> #REF! | FG178: =#REF! -> #REF! | FH178: =#REF! -> #REF! | FI178: =#REF! -> #REF!
FB179: 3 | FC179: 21 | FD179: =#REF! -> #REF! | FE179: =#REF! -> #REF! | FF179: =#REF! -> #REF! | FG179: =#REF! -> #REF! | FH179: =#REF! -> #REF! | FI179: =#REF! -> #REF!
FB180: 3 | FC180: 22 | FD180: =#REF! -> #REF! | FE180: =#REF! -> #REF! | FF180: =#REF! -> #REF! | FG180: =#REF! -> #REF! | FH180: =#REF! -> #REF! | FI180: =#REF! -> #REF!
FB181: 3 | FC181: 23 | FD181: =#REF! -> #REF! | FE181: =#REF! -> #REF! | FF181: =#REF! -> #REF! | FG181: =#REF! -> #REF! | FH181: =#REF! -> #REF! | FI181: =#REF! -> #REF!
FB400: NO | FC400: 明細NO | FD400: 品名 | FE400: 数量 | FF400: 単位 | FG400: 単価 | FH400: 金額 | FI400: 備考

Sheet 城東営業所展示会
M2: CODE | AA2: 請 求 書
E3: 〒160-8511 | AL3: No. | AN3: FL2507175
D4: 東京都新宿区四谷4-1
AG6: 令和 | AI6: 7 | AL6: 年 | AM6: 7 | AO6: 月 | AP6: 17 | AR6: 日
D7: 大塚刷毛製造株式会社 | T7: 様
D11: 期日 | H11: 45948
D13: 場所 | H13: 城東営業所 | AB13: 振込先： | AE13: 十六銀行 柳ヶ瀬支店 普通：0777577
D15: 現金支払 | I15: 末締め末現金払い | AB15: 名義： | AE15: ｶ)ﾘﾝｼｭﾝﾄﾞｳ
AB17: 担当者 | AF17: 田中 健吾
J19: =H39 -> 96250
D20: 税込合計 | J20: =H39 -> 96250
B22: 見積書有効期限発効後60日
B24: 品 名 | T24: 数 量 | AA24: 税別単価 | AF24: 金 額 | AM24: 備 考
B26: 展示会参加諸経費 10/17金曜 10/18土曜 | AF26: =IF(T26="",1*AA26,T26*AA26) -> 0 | AM26: 城東営業所
B27: 公共交通費 往復 | X27: 一式 | AA27: 25000 | AF27: =IF(T27="",1*AA27,T27*AA27) -> 25000
B28: 宿泊費 1泊2日 1名分 | T28: 1 | X28: 一式 | AA28: 15000 | AF28: =IF(T28="",1*AA28,T28*AA28) -> 15000
B29: 日当１日1名分 10/17平日 | T29: 1 | X29: 一式 | AA29: 50000 | AF29: =IF(T29="",1*AA29,T29*AA29) -> 50000
B30: 日当１日1名分 10/18土日 | T30: 1 | X30: 一式 | AA30: 75000 | AF30: =IF(T30="",1*AA30,T30*AA30) -> 75000
B31: 展示会参加デモ用消耗品費 事前送付 | X31: 一式 | AA31: 10000 | AF31: =IF(T31="",1*AA31,T31*AA31) -> 10000
AF32: =IF(T32="",1*AA32,T32*AA32) -> 0
AF33: =IF(T33="",1*AA33,T33*AA33) -> 0
AF34: =IF(T34="",1*AA34,T34*AA34) -> 0
B35: 出展協力50％値引き | X35: 一式 | AA35: -87500 | AF35: =IF(T35="",1*AA35,T35*AA35) -> -87500
B36: 電源 遮光パネル 窒素 本体一式 御社手配 | X36: 一式 | AF36: =IF(T36="",1*AA36,T36*AA36) -> 0
AF37: =IF(T37="",1*AA37,T37*AA37) -> 0
B38: 消費税10% | H38: =AA38*0.1 -> 8750 | T38: 小 計 | AA38: =SUM(AF26:AL37) -> 87500
B39: 合計金額 | H39: =CK115+H38 -> 96250
B40: 摘要：
B41: 城東営業所 〒121-0064 東京都足立区保木間１丁目３−１２
P56: =SUM(CK115:CQ115) -> 87500
FB100: NO | FC100: 明細NO | FD100: 品名 | FE100: 数量 | FF100: 単位 | FG100: 単位 | FH100: 金額 | FI100: 備考
FB101: 0 | FC101: 1 | FD101: =B26 -> 展示会参加諸経費 10/17金曜 10/18土曜 | FE101: =T26 -> 0 | FF101: =X26 -> 0 | FG101: =AA26 -> 0 | FH101: =AF26 -> 0 | FI101: =AM26 -> 城東営業所
EM102: ON | FB102: 0 | FC102: 2 | FD102: =B27 -> 公共交通費 往復 | FE102: =T27 -> 0 | FF102: =X27 -> 一式 | FG102: =AA27 -> 25000 | FH102: =AF27 -> 25000 | FI102: =AM27 -> 0
CE103: 制御 | CI103: 総計 | CS103: 単位 | CW103: 消費税 | DD103: タイトル | DM103: ﾏｽﾀﾊﾞｯｸｱｯﾌﾟ | EM103: OFF | FB103: 0 | FC103: 3 | FD103: =B28 -> 宿泊費 1泊2日 1名分 | FE103: =T28 -> 1 | FF103: =X28 -> 一式 | FG103: =AA28 -> 15000 | FH103: =AF28 -> 15000 | FI103: =AM28 -> 0
CE104: 3 | CI104: 0 | CK104: =AA38 -> 87500 | CS104: 台 | CW104: 5 | CY104: ％ | DD104: 御 見 積 書 | DM104: ON | FB104: 0 | FC104: 4 | FD104: =B29 -> 日当１日1名分 10/17平日 | FE104: =T29 -> 1 | FF104: =X29 -> 一式 | FG104: =AA29 -> 50000 | FH104: =AF29 -> 50000 | FI104: =AM29 -> 0
CE105: =MAX(FB401:FB642) -> 0 | CI105: 1 | CK105: =IF(ISERROR(#REF!),0,#REF!) -> 0 | CS105: 個 | DD105: 納 品 書 | FB105: 0 | FC105: 5 | FD105: =#REF! -> #REF! | FE105: =T30 -> 1 | FF105: =X30 -> 一式 | FG105: =AA30 -> 75000 | FH105: =AF30 -> 75000 | FI105: =AM30 -> 0
CE106: 1 | CI106: 2 | CK106: =IF(ISERROR(#REF!),0,#REF!) -> 0 | CS106: 一式 | CV106: 画面表示 | DD106: 納 品 書 （控） | DM106: ﾃﾞｰﾀ保存ｼｰﾄ | FB106: 0 | FC106: 6 | FD106: =#REF! -> #REF! | FE106: =T31 -> 0 | FF106: =X31 -> 一式 | FG106: =AA31 -> 10000 | FH106: =AF31 -> 10000 | FI106: =AM31 -> 0
CE107: 0 | CI107: 3 | CK107: =IF(ISERROR(#REF!),0,#REF!) -> 0 | CS107: 冊 | CV107: ① | CW107: 100 | CZ107: ％ | DD107: 請 求 書 | DM107: データ保存 1.xls | FB107: 0 | FC107: 7 | FD107: =#REF! -> #REF! | FE107: =T32 -> 0 | FF107: =X32 -> 0 | FG107: =AA32 -> 0 | FH107: =AF32 -> 0 | FI107: =AM32 -> 0
CE108: 敬称 | CI108: 4 | CS108: 箱 | CV108: ② | CW108: 80 | CZ108: ％ | DD108: 請 求 書 （控） | DM108: 鑑 | FB108: 0 | FC108: 8 | FD108: =B31 -> 展示会参加デモ用消耗品費 事前送付 | FE108: =T33 -> 0 | FF108: =X33 -> 0 | FG108: =AA33 -> 0 | FH108: =AF33 -> 0 | FI108: =AM33 -> 0
CE109: 御中 | CI109: 5 | CS109: C/S | DM109: 明細 | FB109: 0 | FC109: 9 | FD109: =B34 -> 0 | FE109: =T34 -> 0 | FF109: =X34 -> 0 | FG109: =AA34 -> 0 | FH109: =AF34 -> 0 | FI109: =AM34 -> 0
CE110: 様 | CI110: 6 | CS110: SET | CV110: 画像ファイル名 | DE110: 画像名 | FB110: 0 | FC110: 10 | FD110: =B35 -> 出展協力50％値引き | FE110: =T35 -> 0 | FF110: =X35 -> 一式 | FG110: =AA35 -> -87500 | FH110: =AF35 -> -87500 | FI110: =AM35 -> 0
CE111: 殿 | CI111: 7 | CS111: 本 | CV111: ① | CW111: 会社角印.gif | DE111: 会社角印 | FB111: 0 | FC111: 11 | FD111: =B36 -> 電源 遮光パネル 窒素 本体一式 御社手配 | FE111: =T36 -> 0 | FF111: =X36 -> 一式 | FG111: =AA36 -> 0 | FH111: =AF36 -> 0 | FI111: =AM36 -> 0
CI112: 8 | CS112: 束 | CV112: ② | CW112: 林印.png | DE112: 林印 | FB112: 0 | FC112: 12 | FD112: =B37 -> 0 | FE112: =T37 -> 0 | FF112: =X37 -> 0 | FG112: =AA37 -> 0 | FH112: =AF37 -> 0 | FI112: =AM37 -> 0
CI113: 9 | CS113: 枚 | CV113: ③ | CW113: 佐藤.png | DE113: 佐藤印 | FB113: 1 | FC113: 1 | FD113: =#REF! -> #REF! | FE113: =#REF! -> #REF! | FF113: =#REF! -> #REF! | FG113: =#REF! -> #REF! | FH113: =#REF! -> #REF! | FI113: =#REF! -> #REF!
CI114: 10 | CS114: ﾊﾟｯｸ | CV114: ④ | CW114: 青木印.gif | DE114: 青木印 | FB114: 1 | FC114: 2 | FD114: =#REF! -> #REF! | FE114: =#REF! -> #REF! | FF114: =#REF! -> #REF! | FG114: =#REF! -> #REF! | FH114: =#REF! -> #REF! | FI114: =#REF! -> #REF!
CI115: 計 | CK115: =SUM(CK104:CQ114) -> 87500 | CS115: ｷｯﾄ | CV115: ⑤ | CW115: 中田印.gif | DE115: 中田印 | FB115: 1 | FC115: 3 | FD115: =#REF! -> #REF! | FE115: =#REF! -> #REF! | FF115: =#REF! -> #REF! | FG115: =#REF! -> #REF! | FH115: =#REF! -> #REF! | FI115: =#REF! -> #REF!
FB116: 1 | FC116: 4 | FD116: =#REF! -> #REF! | FE116: =#REF! -> #REF! | FF116: =#REF! -> #REF! | FG116: =#REF! -> #REF! | FH116: =#REF! -> #REF! | FI116: =#REF! -> #REF!
FB117: 1 | FC117: 5 | FD117: =#REF! -> #REF! | FE117: =#REF! -> #REF! | FF117: =#REF! -> #REF! | FG117: =#REF! -> #REF! | FH117: =#REF! -> #REF! | FI117: =#REF! -> #REF!
FB118: 1 | FC118: 6 | FD118: =#REF! -> #REF! | FE118: =#REF! -> #REF! | FF118: =#REF! -> #REF! | FG118: =#REF! -> #REF! | FH118: =#REF! -> #REF! | FI118: =#REF! -> #REF!
CI119: マスタパス | CM119: C:\Documents and Settings\sato\My Documents\シンプル見積書\ | DM119: ﾏｽﾀ | DO119: マスタ 1.xls | FB119: 1 | FC119: 7 | FD119: =#REF! -> #REF! | FE119: =#REF! -> #REF! | FF119: =#REF! -> #REF! | FG119: =#REF! -> #REF! | FH119: =#REF! -> #REF! | FI119: =#REF! -> #REF!
CI120: データﾊﾟｽ | FB120: 1 | FC120: 8 | FD120: =#REF! -> #REF! | FE120: =#REF! -> #REF! | FF120: =#REF! -> #REF! | FG120: =#REF! -> #REF! | FH120: =#REF! -> #REF! | FI120: =#REF! -> #REF!
FB121: 1 | FC121: 9 | FD121: =#REF! -> #REF! | FE121: =#REF! -> #REF! | FF121: =#REF! -> #REF! | FG121: =#REF! -> #REF! | FH121: =#REF! -> #REF! | FI121: =#REF! -> #REF!
FB122: 1 | FC122: 10 | FD122: =#REF! -> #REF! | FE122: =#REF! -> #REF! | FF122: =#REF! -> #REF! | FG122: =#REF! -> #REF! | FH122: =#REF! -> #REF! | FI122: =#REF! -> #REF!
FB123: 1 | FC123: 11 | FD123: =#REF! -> #REF! | FE123: =#REF! -> #REF! | FF123: =#REF! -> #REF! | FG123: =#REF! -> #REF! | FH123: =#REF! -> #REF! | FI123: =#REF! -> #REF!
FB124: 1 | FC124: 12 | FD124: =#REF! -> #REF! | FE124: =#REF! -> #REF! | FF124: =#REF! -> #REF! | FG124: =#REF! -> #REF! | FH124: =#REF! -> #REF! | FI124: =#REF! -> #REF!
FB125: 1 | FC125: 13 | FD125: =#REF! -> #REF! | FE125: =#REF! -> #REF! | FF125: =#REF! -> #REF! | FG125: =#REF! -> #REF! | FH125: =#REF! -> #REF! | FI125: =#REF! -> #REF!
FB126: 1 | FC126: 14 | FD126: =#REF! -> #REF! | FE126: =#REF! -> #REF! | FF126: =#REF! -> #REF! | FG126: =#REF! -> #REF! | FH126: =#REF! -> #REF! | FI126: =#REF! -> #REF!
FB127: 1 | FC127: 15 | FD127: =#REF! -> #REF! | FE127: =#REF! -> #REF! | FF127: =#REF! -> #REF! | FG127: =#REF! -> #REF! | FH127: =#REF! -> #REF! | FI127: =#REF! -> #REF!
FB128: 1 | FC128: 16 | FD128: =#REF! -> #REF! | FE128: =#REF! -> #REF! | FF128: =#REF! -> #REF! | FG128: =#REF! -> #REF! | FH128: =#REF! -> #REF! | FI128: =#REF! -> #REF!
FB129: 1 | FC129: 17 | FD129: =#REF! -> #REF! | FE129: =#REF! -> #REF! | FF129: =#REF! -> #REF! | FG129: =#REF! -> #REF! | FH129: =#REF! -> #REF! | FI129: =#REF! -> #REF!
FB130: 1 | FC130: 18 | FD130: =#REF! -> #REF! | FE130: =#REF! -> #REF! | FF130: =#REF! -> #REF! | FG130: =#REF! -> #REF! | FH130: =#REF! -> #REF! | FI130: =#REF! -> #REF!
FB131: 1 | FC131: 19 | FD131: =#REF! -> #REF! | FE131: =#REF! -> #REF! | FF131: =#REF! -> #REF! | FG131: =#REF! -> #REF! | FH131: =#REF! -> #REF! | FI131: =#REF! -> #REF!
FB132: 1 | FC132: 20 | FD132: =#REF! -> #REF! | FE132: =#REF! -> #REF! | FF132: =#REF! -> #REF! | FG132: =#REF! -> #REF! | FH132: =#REF! -> #REF! | FI132: =#REF! -> #REF!
... FB173: 3 | FC173: 15 | FD173: =#REF! -> #REF! | FE173: =#REF! -> #REF! | FF173: =#REF! -> #REF! | FG173: =#REF! -> #REF! | FH173: =#REF! -> #REF! | FI173: =#REF! -> #REF!
P174: 0 | Q174: 15 | R174: 32 | S174: 117 | T174: 41 | U174: 124 | FB174: 3 | FC174: 16 | FD174: =#REF! -> #REF! | FE174: =#REF! -> #REF! | FF174: =#REF! -> #REF! | FG174: =#REF! -> #REF! | FH174: =#REF! -> #REF! | FI174: =#REF! -> #REF!
FB175: 3 | FC175: 17 | FD175: =#REF! -> #REF! | FE175: =#REF! -> #REF! | FF175: =#REF! -> #REF! | FG175: =#REF! -> #REF! | FH175: =#REF! -> #REF! | FI175: =#REF! -> #REF!
P176: 00-F-20-75-29-7C | FB176: 3 | FC176: 18 | FD176: =#REF! -> #REF! | FE176: =#REF! -> #REF! | FF176: =#REF! -> #REF! | FG176: =#REF! -> #REF! | FH176: =#REF! -> #REF! | FI176: =#REF! -> #REF!
FB177: 3 | FC177: 19 | FD177: =#REF! -> #REF! | FE177: =#REF! -> #REF! | FF177: =#REF! -> #REF! | FG177: =#REF! -> #REF! | FH177: =#REF! -> #REF! | FI177: =#REF! -> #REF!
FB178: 3 | FC178: 20 | FD178: =#REF! -> #REF! | FE178: =#REF! -> #REF! | FF178: =#REF! -> #REF! | FG178: =#REF! -> #REF! | FH178: =#REF! -> #REF! | FI178: =#REF! -> #REF!
FB179: 3 | FC179: 21 | FD179: =#REF! -> #REF! | FE179: =#REF! -> #REF! | FF179: =#REF! -> #REF! | FG179: =#REF! -> #REF! | FH179: =#REF! -> #REF! | FI179: =#REF! -> #REF!
FB180: 3 | FC180: 22 | FD180: =#REF! -> #REF! | FE180: =#REF! -> #REF! | FF180: =#REF! -> #REF! | FG180: =#REF! -> #REF! | FH180: =#REF! -> #REF! | FI180: =#REF! -> #REF!
FB181: 3 | FC181: 23 | FD181: =#REF! -> #REF! | FE181: =#REF! -> #REF! | FF181: =#REF! -> #REF! | FG181: =#REF! -> #REF! | FH181: =#REF! -> #REF! | FI181: =#REF! -> #REF!
FB400: NO | FC400: 明細NO | FD400: 品名 | FE400: 数量 | FF400: 単位 | FG400: 単価 | FH400: 金額 | FI400: 備考

Sheet フジペックス栃木営業所
M2: CODE | AA2: 御 見 積 書
E3: 〒160-8511 | AL3: No. | AN3: FL2507186
D4: 東京都新宿区四谷4-1
AG6: 令和 | AI6: 7 | AL6: 年 | AM6: 7 | AO6: 月 | AP6: 18 | AR6: 日
D7: 大塚刷毛製造株式会社 | T7: 様
D11: 期日 | H11: 2025/9/6-7
D13: 場所 | H13: 群馬県太田市吉沢町1058-5 | AB13: 振込先： | AE13: 十六銀行 柳ヶ瀬支店 普通：0777577
D15: 現金支払 | I15: 末締め末現金払い | AB15: 名義： | AE15: ｶ)ﾘﾝｼｭﾝﾄﾞｳ
AB17: 担当者 | AF17: 田中 健吾
J19: =H39 -> 220000
D20: 税込合計 | J20: =H39 -> 220000
B24: 品 名 | T24: 数 量 | AA24: 税別単価 | AF24: 金 額 | AM24: 備 考
B26: RSD-SUNMAX-FL-LCW-PRO 講習会 | AF26: =IF(T26="",1*AA26,T26*AA26) -> 0
B27: 交通費 往復 岐阜-太田市 商用車使用 | X27: 一式 | AA27: 50000 | AF27: =IF(T27="",1*AA27,T27*AA27) -> 50000
B28: ETC利用料金 | X28: 一式 | AA28: 19400 | AF28: =IF(T28="",1*AA28,T28*AA28) -> 19400
B29: 宿泊費 1泊2日 2名分 | X29: 一式 | AA29: 30000 | AF29: =IF(T29="",1*AA29,T29*AA29) -> 30000
B30: 日当１日1名分 土日 | T30: 4 | X30: 一式 | AA30: 75000 | AF30: =IF(T30="",1*AA30,T30*AA30) -> 300000
B31: FL-LCW デモ機展示設置費用LCW1.5kw | X31: 一式 | AA31: 20000 | AF31: =IF(T31="",1*AA31,T31*AA31) -> 20000
B32: 展示会参加デモ用消耗品費 | X32: 一式 | AA32: 15000 | AF32: =IF(T32="",1*AA32,T32*AA32) -> 15000
B33: 保護メガネ５人分程度、手袋、溶接台 弊社手配 | X33: 一式 | AA33: 10000 | AF33: =IF(T33="",1*AA33,T33*AA33) -> 10000
B34: 追加値引き | X34: 一式 | AA34: -22200 | AF34: =IF(T34="",1*AA34,T34*AA34) -> -22200
B35: 出展協力50％値引き | X35: 一式 | AA35: -222200 | AF35: =IF(T35="",1*AA35,T35*AA35) -> -222200
B36: 電源 遮光パネル 窒素 御社手配 | AF36: =IF(T36="",1*AA36,T36*AA36) -> 0
B37: デモ機の搬入撤収時男性お手伝い要します。 | AF37: =IF(T37="",1*AA37,T37*AA37) -> 0
B38: 消費税10% | H38: =AA38*0.1 -> 20000 | T38: 小 計 | AA38: =SUM(AF26:AL37) -> 200000
B39: 合計金額 | H39: =CK115+H38 -> 220000
B40: 摘要： | E40: 発注書No2489059
B41: 場所 株式会社フジペックス栃木営業所 栃木県下野市下石橋148-4
P56: =SUM(CK115:CQ115) -> 200000
FB100: NO | FC100: 明細NO | FD100: 品名 | FE100: 数量 | FF100: 単位 | FG100: 単位 | FH100: 金額 | FI100: 備考
FB101: 0 | FC101: 1 | FD101: =B26 -> RSD-SUNMAX-FL-LCW-PRO 講習会 | FE101: =T26 -> 0 | FF101: =X26 -> 0 | FG101: =AA26 -> 0 | FH101: =AF26 -> 0 | FI101: =AM26 -> 0
EM102: ON | FB102: 0 | FC102: 2 | FD102: =B27 -> 交通費 往復 岐阜-太田市 商用車使用 | FE102: =T27 -> 0 | FF102: =X27 -> 一式 | FG102: =AA27 -> 50000 | FH102: =AF27 -> 50000 | FI102: =AM27 -> 0
CE103: 制御 | CI103: 総計 | CS103: 単位 | CW103: 消費税 | DD103: タイトル | DM103: ﾏｽﾀﾊﾞｯｸｱｯﾌﾟ | EM103: OFF | FB103: 0 | FC103: 3 | FD103: =B28 -> ETC利用料金 | FE103: =T28 -> 0 | FF103: =X28 -> 一式 | FG103: =AA28 -> 19400 | FH103: =AF28 -> 19400 | FI103: =AM28 -> 0
CE104: 3 | CI104: 0 | CK104: =AA38 -> 200000 | CS104: 台 | CW104: 5 | CY104: ％ | DD104: 御 見 積 書 | DM104: ON | FB104: 0 | FC104: 4 | FD104: =B29 -> 宿泊費 1泊2日 2名分 | FE104: =T29 -> 0 | FF104: =X29 -> 一式 | FG104: =AA29 -> 30000 | FH104: =AF29 -> 30000 | FI104: =AM29 -> 0
CE105: =MAX(FB401:FB642) -> 0 | CI105: 1 | CK105: =IF(ISERROR(#REF!),0,#REF!) -> 0 | CS105: 個 | DD105: 納 品 書 | FB105: 0 | FC105: 5 | FD105: =#REF! -> #REF! | FE105: =T30 -> 4 | FF105: =X30 -> 一式 | FG105: =AA30 -> 75000 | FH105: =AF30 -> 300000 | FI105: =AM30 -> 0
CE106: 1 | CI106: 2 | CK106: =IF(ISERROR(#REF!),0,#REF!) -> 0 | CS106: 一式 | CV106: 画面表示 | DD106: 納 品 書 （控） | DM106: ﾃﾞｰﾀ保存ｼｰﾄ | FB106: 0 | FC106: 6 | FD106: =#REF! -> #REF! | FE106: =T31 -> 0 | FF106: =X31 -> 一式 | FG106: =AA31 -> 20000 | FH106: =AF31 -> 20000 | FI106: =AM31 -> 0
CE107: 0 | CI107: 3 | CK107: =IF(ISERROR(#REF!),0,#REF!) -> 0 | CS107: 冊 | CV107: ① | CW107: 100 | CZ107: ％ | DD107: 請 求 書 | DM107: データ保存 1.xls | FB107: 0 | FC107: 7 | FD107: =#REF! -> #REF! | FE107: =T32 -> 0 | FF107: =X32 -> 一式 | FG107: =AA32 -> 15000 | FH107: =AF32 -> 15000 | FI107: =AM32 -> 0
CE108: 敬称 | CI108: 4 | CS108: 箱 | CV108: ② | CW108: 80 | CZ108: ％ | DD108: 請 求 書 （控） | DM108: 鑑 | FB108: 0 | FC108: 8 | FD108: =B31 -> FL-LCW デモ機展示設置費用LCW1.5kw | FE108: =T33 -> 0 | FF108: =X33 -> 一式 | FG108: =AA33 -> 10000 | FH108: =AF33 -> 10000 | FI108: =AM33 -> 0
CE109: 御中 | CI109: 5 | CS109: C/S | DM109: 明細 | FB109: 0 | FC109: 9 | FD109: =B34 -> 追加値引き | FE109: =T34 -> 0 | FF109: =X34 -> 一式 | FG109: =AA34 -> -22200 | FH109: =AF34 -> -22200 | FI109: =AM34 -> 0
CE110: 様 | CI110: 6 | CS110: SET | CV110: 画像ファイル名 | DE110: 画像名 | FB110: 0 | FC110: 10 | FD110: =B35 -> 出展協力50％値引き | FE110: =T35 -> 0 | FF110: =X35 -> 一式 | FG110: =AA35 -> -222200 | FH110: =AF35 -> -222200 | FI110: =AM35 -> 0
CE111: 殿 | CI111: 7 | CS111: 本 | CV111: ① | CW111: 会社角印.gif | DE111: 会社角印 | FB111: 0 | FC111: 11 | FD111: =B36 -> 電源 遮光パネル 窒素 御社手配 | FE111: =T36 -> 0 | FF111: =X36 -> 0 | FG111: =AA36 -> 0 | FH111: =AF36 -> 0 | FI111: =AM36 -> 0
CI112: 8 | CS112: 束 | CV112: ② | CW112: 林印.png | DE112: 林印 | FB112: 0 | FC112: 12 | FD112: =B37 -> デモ機の搬入撤収時男性お手伝い要します。 | FE112: =T37 -> 0 | FF112: =X37 -> 0 | FG112: =AA37 -> 0 | FH112: =AF37 -> 0 | FI112: =AM37 -> 0
CI113: 9 | CS113: 枚 | CV113: ③ | CW113: 佐藤.png | DE113: 佐藤印 | FB113: 1 | FC113: 1 | FD113: =#REF! -> #REF! | FE113: =#REF! -> #REF! | FF113: =#REF! -> #REF! | FG113: =#REF! -> #REF! | FH113: =#REF! -> #REF! | FI113: =#REF! -> #REF!
CI114: 10 | CS114: ﾊﾟｯｸ | CV114: ④ | CW114: 青木印.gif | DE114: 青木印 | FB114: 1 | FC114: 2 | FD114: =#REF! -> #REF! | FE114: =#REF! -> #REF! | FF114: =#REF! -> #REF! | FG114: =#REF! -> #REF! | FH114: =#REF! -> #REF! | FI114: =#REF! -> #REF!
CI115: 計 | CK115: =SUM(CK104:CQ114) -> 200000 | CS115: ｷｯﾄ | CV115: ⑤ | CW115: 中田印.gif | DE115: 中田印 | FB115: 1 | FC115: 3 | FD115: =#REF! -> #REF! | FE115: =#REF! -> #REF! | FF115: =#REF! -> #REF! | FG115: =#REF! -> #REF! | FH115: =#REF! -> #REF! | FI115: =#REF! -> #REF!
FB116: 1 | FC116: 4 | FD116: =#REF! -> #REF! | FE116: =#REF! -> #REF! | FF116: =#REF! -> #REF! | FG116: =#REF! -> #REF! | FH116: =#REF! -> #REF! | FI116: =#REF! -> #REF!
FB117: 1 | FC117: 5 | FD117: =#REF! -> #REF! | FE117: =#REF! -> #REF! | FF117: =#REF! -> #REF! | FG117: =#REF! -> #REF! | FH117: =#REF! -> #REF! | FI117: =#REF! -> #REF!
FB118: 1 | FC118: 6 | FD118: =#REF! -> #REF! | FE118: =#REF! -> #REF! | FF118: =#REF! -> #REF! | FG118: =#REF! -> #REF! | FH118: =#REF! -> #REF! | FI118: =#REF! -> #REF!
CI119: マスタパス | CM119: C:\Documents and Settings\sato\My Documents\シンプル見積書\ | DM119: ﾏｽﾀ | DO119: マスタ 1.xls | FB119: 1 | FC119: 7 | FD119: =#REF! -> #REF! | FE119: =#REF! -> #REF! | FF119: =#REF! -> #REF! | FG119: =#REF! -> #REF! | FH119: =#REF! -> #REF! | FI119: =#REF! -> #REF!
CI120: データﾊﾟｽ | FB120: 1 | FC120: 8 | FD120: =#REF! -> #REF! | FE120: =#REF! -> #REF! | FF120: =#REF! -> #REF! | FG120: =#REF! -> #REF! | FH120: =#REF! -> #REF! | FI120: =#REF! -> #REF!
FB121: 1 | FC121: 9 | FD121: =#REF! -> #REF! | FE121: =#REF! -> #REF! | FF121: =#REF! -> #REF! | FG121: =#REF! -> #REF! | FH121: =#REF! -> #REF! | FI121: =#REF! -> #REF!
FB122: 1 | FC122: 10 | FD122: =#REF! -> #REF! | FE122: =#REF! -> #REF! | FF122: =#REF! -> #REF! | FG122: =#REF! -> #REF! | FH122: =#REF! -> #REF! | FI122: =#REF! -> #REF!
FB123: 1 | FC123: 11 | FD123: =#REF! -> #REF! | FE123: =#REF! -> #REF! | FF123: =#REF! -> #REF! | FG123: =#REF! -> #REF! | FH123: =#REF! -> #REF! | FI123: =#REF! -> #REF!
FB124: 1 | FC124: 12 | FD124: =#REF! -> #REF! | FE124: =#REF! -> #REF! | FF124: =#REF! -> #REF! | FG124: =#REF! -> #REF! | FH124: =#REF! -> #REF! | FI124: =#REF! -> #REF!
FB125: 1 | FC125: 13 | FD125: =#REF! -> #REF! | FE125: =#REF! -> #REF! | FF125: =#REF! -> #REF! | FG125: =#REF! -> #REF! | FH125: =#REF! -> #REF! | FI125: =#REF! -> #REF!
FB126: 1 | FC126: 14 | FD126: =#REF! -> #REF! | FE126: =#REF! -> #REF! | FF126: =#REF! -> #REF! | FG126: =#REF! -> #REF! | FH126: =#REF! -> #REF! | FI126: =#REF! -> #REF!
FB127: 1 | FC127: 15 | FD127: =#REF! -> #REF! | FE127: =#REF! -> #REF! | FF127: =#REF! -> #REF! | FG127: =#REF! -> #REF! | FH127: =#REF! -> #REF! | FI127: =#REF! -> #REF!
FB128: 1 | FC128: 16 | FD128: =#REF! -> #REF! | FE128: =#REF! -> #REF! | FF128: =#REF! -> #REF! | FG128: =#REF! -> #REF! | FH128: =#REF! -> #REF! | FI128: =#REF! -> #REF!
FB129: 1 | FC129: 17 | FD129: =#REF! -> #REF! | FE129: =#REF! -> #REF! | FF129: =#REF! -> #REF! | FG129: =#REF! -> #REF! | FH129: =#REF! -> #REF! | FI129: =#REF! -> #REF!
FB130: 1 | FC130: 18 | FD130: =#REF! -> #REF! | FE130: =#REF! -> #REF! | FF130: =#REF! -> #REF! | FG130: =#REF! -> #REF! | FH130: =#REF! -> #REF! | FI130: =#REF! -> #REF!
FB131: 1 | FC131: 19 | FD131: =#REF! -> #REF! | FE131: =#REF! -> #REF! | FF131: =#REF! -> #REF! | FG131: =#REF! -> #REF! | FH131: =#REF! -> #REF! | FI131: =#REF! -> #REF!
FB132: 1 | FC132: 20 | FD132: =#REF! -> #REF! | FE132: =#REF! -> #REF! | FF132: =#REF! -> #REF! | FG132: =#REF! -> #REF! | FH132: =#REF! -> #REF! | FI132: =#REF! -> #REF!
... FB173: 3 | FC173: 15 | FD173: =#REF! -> #REF! | FE173: =#REF! -> #REF! | FF173: =#REF! -> #REF! | FG173: =#REF! -> #REF! | FH173: =#REF! -> #REF! | FI173: =#REF! -> #REF!
P174: 0 | Q174: 15 | R174: 32 | S174: 117 | T174: 41 | U174: 124 | FB174: 3 | FC174: 16 | FD174: =#REF! -> #REF! | FE174: =#REF! -> #REF! | FF174: =#REF! -> #REF! | FG174: =#REF! -> #REF! | FH174: =#REF! -> #REF! | FI174: =#REF! -> #REF!
FB175: 3 | FC175: 17 | FD175: =#REF! -> #REF! | FE175: =#REF! -> #REF! | FF175: =#REF! -> #REF! | FG175: =#REF! -> #REF! | FH175: =#REF! -> #REF! | FI175: =#REF! -> #REF!
P176: 00-F-20-75-29-7C | FB176: 3 | FC176: 18 | FD176: =#REF! -> #REF! | FE176: =#REF! -> #REF! | FF176: =#REF! -> #REF! | FG176: =#REF! -> #REF! | FH176: =#REF! -> #REF! | FI176: =#REF! -> #REF!
FB177: 3 | FC177: 19 | FD177: =#REF! -> #REF! | FE177: =#REF! -> #REF! | FF177: =#REF! -> #REF! | FG177: =#REF! -> #REF! | FH177: =#REF! -> #REF! | FI177: =#REF! -> #REF!
FB178: 3 | FC178: 20 | FD178: =#REF! -> #REF! | FE178: =#REF! -> #REF! | FF178: =#REF! -> #REF! | FG178: =#REF! -> #REF! | FH178: =#REF! -> #REF! | FI178: =#REF! -> #REF!
FB179: 3 | FC179: 21 | FD179: =#REF! -> #REF! | FE179: =#REF! -> #REF! | FF179: =#REF! -> #REF! | FG179: =#REF! -> #REF! | FH179: =#REF! -> #REF! | FI179: =#REF! -> #REF!
FB180: 3 | FC180: 22 | FD180: =#REF! -> #REF! | FE180: =#REF! -> #REF! | FF180: =#REF! -> #REF! | FG180: =#REF! -> #REF! | FH180: =#REF! -> #REF! | FI180: =#REF! -> #REF!
FB181: 3 | FC181: 23 | FD181: =#REF! -> #REF! | FE181: =#REF! -> #REF! | FF181: =#REF! -> #REF! | FG181: =#REF! -> #REF! | FH181: =#REF! -> #REF! | FI181: =#REF! -> #REF!
FB400: NO | FC400: 明細NO | FD400: 品名 | FE400: 数量 | FF400: 単位 | FG400: 単価 | FH400: 金額 | FI400: 備考

Sheet 展示会準備項目
D3: 一覧 | AL3: No.
C5: 準備 品 名 | U5: 数 量 | AB5: 単 価 | AG5: 金 額 | AN5: 備 考
C7: 遮光パネル／保護カーテン | U7: 1 | AG7: =IF(U7="",1*AB7,U7*AB7) -> 0 | AN7: 弊社準備
C8: 三相200V 30A ストレートタイプコンセント | U8: 1 | AG8: =IF(U8="",1*AB8,U8*AB8) -> 0 | AN8: 御社準備
C9: 100ｖ 10Aコンセント | U9: 1 | AG9: =IF(U9="",1*AB9,U9*AB9) -> 0 | AN9: 御社準備
B10: 1日1本目安 | C10: 会期中窒素ボンベ(1日1本目安) | U10: 2 | AG10: =IF(U10="",1*AB10,U10*AB10) -> 0 | AN10: 弊社準備
C11: 錆び取り洗浄用デモ実演用素材 | U11: 1 | AG11: =IF(U11="",1*AB11,U11*AB11) -> 0 | AN11: 弊社準備
B12: 自動車外板パネル等 | C12: 溶接ワーク(溶接素材、自動車外板パネル等) | U12: 1 | AG12: =IF(U12="",1*AB12,U12*AB12) -> 0 | AN12: 弊社準備
C13: 展示用の机 | U13: 1 | AG13: =IF(U13="",1*AB13,U13*AB13) -> 0 | AN13: 弊社準備
C14: 溶接机 1台 溶接サンプル | U14: 1 | AG14: =IF(U14="",1*AB14,U14*AB14) -> 0 | AN14: 弊社準備
AG15: =IF(U15="",1*AB15,U15*AB15) -> 0
AG16: =IF(U16="",1*AB16,U16*AB16) -> 0
AG17: =IF(U17="",1*AB17,U17*AB17) -> 0
AG18: =IF(U18="",1*AB18,U18*AB18) -> 0
AG19: =IF(U19="",1*AB19,U19*AB19) -> 0
AG20: =IF(U20="",1*AB20,U20*AB20) -> 0
AG21: =IF(U21="",1*AB21,U21*AB21) -> 0
AG22: =IF(U22="",1*AB22,U22*AB22) -> 0
C23: ボンデ鋼板 2.3t 100x50 | U23: 10 | AB23: 300 | AG23: =IF(U23="",1*AB23,U23*AB23) -> 3000
C24: ZAM材 2.3t 100x50 | U24: 10 | AB24: 350 | AG24: =IF(U24="",1*AB24,U24*AB24) -> 3500
C25: ステンレス 2t 100x50 | U25: 8 | AB25: 400 | AG25: =IF(U25="",1*AB25,U25*AB25) -> 3200
C26: アルミ 2t 100x50 | U26: 8 | AB26: 600 | AG26: =IF(U26="",1*AB26,U26*AB26) -> 4800
C27: 自動車外板パネル 0.8/0/6t | U27: 1 | AB27: 3000 | AG27: =IF(U27="",1*AB27,U27*AB27) -> 3000
AG28: =IF(U28="",1*AB28,U28*AB28) -> 0
B29: FAX感熱紙(A4) | AG29: =IF(U29="",1*AB29,U29*AB29) -> 0
U30: 小 計 | AB30: =SUM(AG7:AG29) -> 17500
CS103: 単位
CS104: =#REF! -> #REF!
CS105: =#REF! -> #REF!
CS106: =#REF! -> #REF!
CS107: =#REF! -> #REF!
CS108: =#REF! -> #REF!
CS109: =#REF! -> #REF!
CS110: =#REF! -> #REF!
CS111: =#REF! -> #REF!
CS112: =#REF! -> #REF!
CS113: =#REF! -> #REF!
CS114: =#REF! -> #REF!
CS115: =#REF! -> #REF!
CS116: =#REF! -> #REF!
CI119: マスタパス | CM119: =#REF! -> #REF! | DO119: =#REF! -> #REF!
CI120: データパス | CM120: =#REF! -> #REF!
P178: =#REF! -> #REF!

Sheet デモ材料費
M2: CODE | AA2: 御 見 積 書
E3: 108-0023 | AL3: No. | AN3: FL2504225
D4: 東京都港区芝浦４－１６－２５
AG6: 令和 | AI6: 7 | AL6: 年 | AM6: 4 | AO6: 月 | AP6: 22 | AR6: 日
D7: 安全自動車株式会社 | T7: 様
D11: 受渡期日 | H11: 展示会開催
D13: 受渡場所 | H13: 東京ビッグサイト | AB13: 振込先： | AE13: 十六銀行 柳ヶ瀬支店 普通：0777577
D15: 現金支払 | I15: 末締め末現金払い | AB15: 名義： | AE15: ｶ)ﾘﾝｼｭﾝﾄﾞｳ
AB17: 担当者 | AF17: 田中 健吾
J19: =H39 -> 39820
D20: 税込合計 | J20: =H39 -> 39820
B22: 見積書有効期限発効後1年
B24: 品 名 | T24: 数 量 | AA24: 税別単価 | AF24: 金 額 | AM24: 備 考
B26: 東京ビッグサイト展示会 | AF26: =IF(T26="",1*AA26,T26*AA26) -> 0
B27: 溶接テスト用材料費 アルミ ステンレス 鉄 | X27: 一式 | AA27: 35000 | AF27: =IF(T27="",1*AA27,T27*AA27) -> 35000
B28: 送料 事前送付 | X28: 一式 | AA28: 1200 | AF28: =IF(T28="",1*AA28,T28*AA28) -> 1200
AF29: =IF(T29="",1*AA29,T29*AA29) -> 0
AF30: =IF(T30="",1*AA30,T30*AA30) -> 0
AF31: =IF(T31="",1*AA31,T31*AA31) -> 0
AF32: =IF(T32="",1*AA32,T32*AA32) -> 0
AF33: =IF(T33="",1*AA33,T33*AA33) -> 0
AF34: =IF(T34="",1*AA34,T34*AA34) -> 0
AF35: =IF(T35="",1*AA35,T35*AA35) -> 0
B38: 消費税10% | H38: =AA38*0.1 -> 3620 | T38: 小 計 | AA38: =SUM(AF26:AL37) -> 36200
B39: 合計金額 | H39: =CK115+H38 -> 39820
B40: 摘要：
P56: =SUM(CK115:CQ115) -> 36200
FB100: NO | FC100: 明細NO | FD100: 品名 | FE100: 数量 | FF100: 単位 | FG100: 単位 | FH100: 金額 | FI100: 備考
FB101: 0 | FC101: 1 | FD101: =B26 -> 東京ビッグサイト展示会 | FE101: =T26 -> 0 | FF101: =X26 -> 0 | FG101: =AA26 -> 0 | FH101: =AF26 -> 0 | FI101: =AM26 -> 0
EM102: ON | FB102: 0 | FC102: 2 | FD102: =B27 -> 溶接テスト用材料費 アルミ ステンレス 鉄 | FE102: =T27 -> 0 | FF102: =X27 -> 一式 | FG102: =AA27 -> 35000 | FH102: =AF27 -> 35000 | FI102: =AM27 -> 0
CE103: 制御 | CI103: 総計 | CS103: 単位 | CW103: 消費税 | DD103: タイトル | DM103: ﾏｽﾀﾊﾞｯｸｱｯﾌﾟ | EM103: OFF | FB103: 0 | FC103: 3 | FD103: =B28 -> 送料 事前送付 | FE103: =T28 -> 0 | FF103: =X28 -> 一式 | FG103: =AA28 -> 1200 | FH103: =AF28 -> 1200 | FI103: =AM28 -> 0
CE104: 3 | CI104: 0 | CK104: =AA38 -> 36200 | CS104: 台 | CW104: 5 | CY104: ％ | DD104: 御 見 積 書 | DM104: ON | FB104: 0 | FC104: 4 | FD104: =B29 -> 0 | FE104: =T29 -> 0 | FF104: =X29 -> 0 | FG104: =AA29 -> 0 | FH104: =AF29 -> 0 | FI104: =AM29 -> 0
CE105: =MAX(FB401:FB642) -> 0 | CI105: 1 | CK105: =IF(ISERROR([1]本体装備品一覧!AB30),0,[1]本体装備品一覧!AB30) -> 0 | CS105: 個 | DD105: 納 品 書 | FB105: 0 | FC105: 5 | FD105: =#REF! -> #REF! | FE105: =T30 -> 0 | FF105: =X30 -> 0 | FG105: =AA30 -> 0 | FH105: =AF30 -> 0 | FI105: =AM30 -> 0
CE106: 1 | CI106: 2 | CK106: =IF(ISERROR(#REF!),0,#REF!) -> 0 | CS106: 一式 | CV106: 画面表示 | DD106: 納 品 書 （控） | DM106: ﾃﾞｰﾀ保存ｼｰﾄ | FB106: 0 | FC106: 6 | FD106: =#REF! -> #REF! | FE106: =T31 -> 0 | FF106: =X31 -> 0 | FG106: =AA31 -> 0 | FH106: =AF31 -> 0 | FI106: =AM31 -> 0
CE107: 0 | CI107: 3 | CK107: =IF(ISERROR(#REF!),0,#REF!) -> 0 | CS107: 冊 | CV107: ① | CW107: 100 | CZ107: ％ | DD107: 請 求 書 | DM107: データ保存 1.xls | FB107: 0 | FC107: 7 | FD107: =#REF! -> #REF! | FE107: =T32 -> 0 | FF107: =X32 -> 0 | FG107: =AA32 -> 0 | FH107: =AF32 -> 0 | FI107: =AM32 -> 0
CE108: 敬称 | CI108: 4 | CS108: 箱 | CV108: ② | CW108: 80 | CZ108: ％ | DD108: 請 求 書 （控） | DM108: 鑑 | FB108: 0 | FC108: 8 | FD108: =B31 -> 0 | FE108: =T33 -> 0 | FF108: =X33 -> 0 | FG108: =AA33 -> 0 | FH108: =AF33 -> 0 | FI108: =AM33 -> 0
CE109: 御中 | CI109: 5 | CS109: C/S | DM109: 明細 | FB109: 0 | FC109: 9 | FD109: =B34 -> 0 | FE109: =T34 -> 0 | FF109: =X34 -> 0 | FG109: =AA34 -> 0 | FH109: =AF34 -> 0 | FI109: =AM34 -> 0
CE110: 様 | CI110: 6 | CS110: SET | CV110: 画像ファイル名 | DE110: 画像名 | FB110: 0 | FC110: 10 | FD110: =B35 -> 0 | FE110: =T35 -> 0 | FF110: =X35 -> 0 | FG110: =AA35 -> 0 | FH110: =AF35 -> 0 | FI110: =AM35 -> 0
CE111: 殿 | CI111: 7 | CS111: 本 | CV111: ① | CW111: 会社角印.gif | DE111: 会社角印 | FB111: 0 | FC111: 11 | FD111: =B36 -> 0 | FE111: =T36 -> 0 | FF111: =X36 -> 0 | FG111: =AA36 -> 0 | FH111: =AF36 -> 0 | FI111: =AM36 -> 0
CI112: 8 | CS112: 束 | CV112: ② | CW112: 林印.png | DE112: 林印 | FB112: 0 | FC112: 12 | FD112: =B37 -> 0 | FE112: =T37 -> 0 | FF112: =X37 -> 0 | FG112: =AA37 -> 0 | FH112: =AF37 -> 0 | FI112: =AM37 -> 0
CI113: 9 | CS113: 枚 | CV113: ③ | CW113: 佐藤.png | DE113: 佐藤印 | FB113: 1 | FC113: 1 | FD113: =[1]本体装備品一覧!$C$7 -> 0 | FE113: =[1]本体装備品一覧!$U$7 -> 0 | FF113: =[1]本体装備品一覧!$Y$7 -> 0 | FG113: =[1]本体装備品一覧!$AB$7 -> 0 | FH113: =[1]本体装備品一覧!$AG$7 -> 0 | FI113: =[1]本体装備品一覧!$AN$7 -> 0
CI114: 10 | CS114: ﾊﾟｯｸ | CV114: ④ | CW114: 青木印.gif | DE114: 青木印 | FB114: 1 | FC114: 2 | FD114: =[1]本体装備品一覧!$C$8 -> 0 | FE114: =[1]本体装備品一覧!$U$8 -> 0 | FF114: =[1]本体装備品一覧!$Y$8 -> 0 | FG114: =[1]本体装備品一覧!$AB$8 -> 0 | FH114: =[1]本体装備品一覧!$AG$8 -> 0 | FI114: =[1]本体装備品一覧!$AN$8 -> 0
CI115: 計 | CK115: =SUM(CK104:CQ114) -> 36200 | CS115: ｷｯﾄ | CV115: ⑤ | CW115: 中田印.gif | DE115: 中田印 | FB115: 1 | FC115: 3 | FD115: =[1]本体装備品一覧!$C$9 -> 0 | FE115: =[1]本体装備品一覧!$U$9 -> 0 | FF115: =[1]本体装備品一覧!$Y$9 -> 0 | FG115: =[1]本体装備品一覧!$AB$9 -> 0 | FH115: =[1]本体装備品一覧!$AG$9 -> 0 | FI115: =[1]本体装備品一覧!$AN$9 -> 0
FB116: 1 | FC116: 4 | FD116: =[1]本体装備品一覧!$C$10 -> 0 | FE116: =[1]本体装備品一覧!$U$10 -> 0 | FF116: =[1]本体装備品一覧!$Y$10 -> 0 | FG116: =[1]本体装備品一覧!$AB$10 -> 0 | FH116: =[1]本体装備品一覧!$AG$10 -> 0 | FI116: =[1]本体装備品一覧!$AN$10 -> 0
FB117: 1 | FC117: 5 | FD117: =[1]本体装備品一覧!$C$11 -> 0 | FE117: =[1]本体装備品一覧!$U$11 -> 0 | FF117: =[1]本体装備品一覧!$Y$11 -> 0 | FG117: =[1]本体装備品一覧!$AB$11 -> 0 | FH117: =[1]本体装備品一覧!$AG$11 -> 0 | FI117: =[1]本体装備品一覧!$AN$11 -> 0
FB118: 1 | FC118: 6 | FD118: =[1]本体装備品一覧!$C$12 -> 0 | FE118: =[1]本体装備品一覧!$U$12 -> 0 | FF118: =[1]本体装備品一覧!$Y$12 -> 0 | FG118: =[1]本体装備品一覧!$AB$12 -> 0 | FH118: =[1]本体装備品一覧!$AG$12 -> 0 | FI118: =[1]本体装備品一覧!$AN$12 -> 0
CI119: マスタパス | CM119: C:\Documents and Settings\sato\My Documents\シンプル見積書\ | DM119: ﾏｽﾀ | DO119: マスタ 1.xls | FB119: 1 | FC119: 7 | FD119: =[1]本体装備品一覧!$C$13 -> 0 | FE119: =[1]本体装備品一覧!$U$13 -> 0 | FF119: =[1]本体装備品一覧!$Y$13 -> 0 | FG119: =[1]本体装備品一覧!$AB$13 -> 0 | FH119: =[1]本体装備品一覧!$AG$13 -> 0 | FI119: =[1]本体装備品一覧!$AN$13 -> 0
CI120: データﾊﾟｽ | FB120: 1 | FC120: 8 | FD120: =[1]本体装備品一覧!$C$14 -> 0 | FE120: =[1]本体装備品一覧!$U$14 -> 0 | FF120: =[1]本体装備品一覧!$Y$14 -> 0 | FG120: =[1]本体装備品一覧!$AB$14 -> 0 | FH120: =[1]本体装備品一覧!$AG$14 -> 0 | FI120: =[1]本体装備品一覧!$AN$14 -> 0
FB121: 1 | FC121: 9 | FD121: =[1]本体装備品一覧!$C$15 -> 0 | FE121: =[1]本体装備品一覧!$U$15 -> 0 | FF121: =[1]本体装備品一覧!$Y$15 -> 0 | FG121: =[1]本体装備品一覧!$AB$15 -> 0 | FH121: =[1]本体装備品一覧!$AG$15 -> 0 | FI121: =[1]本体装備品一覧!$AN$15 -> 0
FB122: 1 | FC122: 10 | FD122: =[1]本体装備品一覧!$C$16 -> 0 | FE122: =[1]本体装備品一覧!$U$16 -> 0 | FF122: =[1]本体装備品一覧!$Y$16 -> 0 | FG122: =[1]本体装備品一覧!$AB$16 -> 0 | FH122: =[1]本体装備品一覧!$AG$16 -> 0 | FI122: =[1]本体装備品一覧!$AN$16 -> 0
FB123: 1 | FC123: 11 | FD123: =[1]本体装備品一覧!$C$17 -> 0 | FE123: =[1]本体装備品一覧!$U$17 -> 0 | FF123: =[1]本体装備品一覧!$Y$17 -> 0 | FG123: =[1]本体装備品一覧!$AB$17 -> 0 | FH123: =[1]本体装備品一覧!$AG$17 -> 0 | FI123: =[1]本体装備品一覧!$AN$17 -> 0
FB124: 1 | FC124: 12 | FD124: =[1]本体装備品一覧!$C$18 -> 0 | FE124: =[1]本体装備品一覧!$U$18 -> 0 | FF124: =[1]本体装備品一覧!$Y$18 -> 0 | FG124: =[1]本体装備品一覧!$AB$18 -> 0 | FH124: =[1]本体装備品一覧!$AG$18 -> 0 | FI124: =[1]本体装備品一覧!$AN$18 -> 0
FB125: 1 | FC125: 13 | FD125: =[1]本体装備品一覧!$C$19 -> 0 | FE125: =[1]本体装備品一覧!$U$19 -> 0 | FF125: =[1]本体装備品一覧!$Y$19 -> 0 | FG125: =[1]本体装備品一覧!$AB$19 -> 0 | FH125: =[1]本体装備品一覧!$AG$19 -> 0 | FI125: =[1]本体装備品一覧!$AN$19 -> 0
FB126: 1 | FC126: 14 | FD126: =[1]本体装備品一覧!$C$20 -> 0 | FE126: =[1]本体装備品一覧!$U$20 -> 0 | FF126: =[1]本体装備品一覧!$Y$20 -> 0 | FG126: =[1]本体装備品一覧!$AB$20 -> 0 | FH126: =[1]本体装備品一覧!$AG$20 -> 0 | FI126: =[1]本体装備品一覧!$AN$20 -> 0
FB127: 1 | FC127: 15 | FD127: =[1]本体装備品一覧!$C$21 -> 0 | FE127: =[1]本体装備品一覧!$U$21 -> 0 | FF127: =[1]本体装備品一覧!$Y$21 -> 0 | FG127: =[1]本体装備品一覧!$AB$21 -> 0 | FH127: =[1]本体装備品一覧!$AG$21 -> 0 | FI127: =[1]本体装備品一覧!$AN$21 -> 0
FB128: 1 | FC128: 16 | FD128: =[1]本体装備品一覧!$C$22 -> 0 | FE128: =[1]本体装備品一覧!$U$22 -> 0 | FF128: =[1]本体装備品一覧!$Y$22 -> 0 | FG128: =[1]本体装備品一覧!$AB$22 -> 0 | FH128: =[1]本体装備品一覧!$AG$22 -> 0 | FI128: =[1]本体装備品一覧!$AN$22 -> 0
FB129: 1 | FC129: 17 | FD129: =[1]本体装備品一覧!$C$23 -> 0 | FE129: =[1]本体装備品一覧!$U$23 -> 0 | FF129: =[1]本体装備品一覧!$Y$23 -> 0 | FG129: =[1]本体装備品一覧!$AB$23 -> 0 | FH129: =[1]本体装備品一覧!$AG$23 -> 0 | FI129: =[1]本体装備品一覧!$AN$23 -> 0
FB130: 1 | FC130: 18 | FD130: =[1]本体装備品一覧!$C$24 -> 0 | FE130: =[1]本体装備品一覧!$U$24 -> 0 | FF130: =[1]本体装備品一覧!$Y$24 -> 0 | FG130: =[1]本体装備品一覧!$AB$24 -> 0 | FH130: =[1]本体装備品一覧!$AG$24 -> 0 | FI130: =[1]本体装備品一覧!$AN$24 -> 0
FB131: 1 | FC131: 19 | FD131: =[1]本体装備品一覧!$C$25 -> 0 | FE131: =[1]本体装備品一覧!$U$25 -> 0 | FF131: =[1]本体装備品一覧!$Y$25 -> 0 | FG131: =[1]本体装備品一覧!$AB$25 -> 0 | FH131: =[1]本体装備品一覧!$AG$25 -> 0 | FI131: =[1]本体装備品一覧!$AN$25 -> 0
FB132: 1 | FC132: 20 | FD132: =[1]本体装備品一覧!$C$26 -> 0 | FE132: =[1]本体装備品一覧!$U$26 -> 0 | FF132: =[1]本体装備品一覧!$Y$26 -> 0 | FG132: =[1]本体装備品一覧!$AB$26 -> 0 | FH132: =[1]本体装備品一覧!$AG$26 -> 0 | FI132: =[1]本体装備品一覧!$AN$26 -> 0
FB133: 1 | FC133: 21 | FD133: =[1]本体装備品一覧!$C$27 -> 0 | FE133: =[1]本体装備品一覧!$U$27 -> 0 | FF133: =[1]本体装備品一覧!$Y$27 -> 0 | FG133: =[1]本体装備品一覧!$AB$27 -> 0 | FH133: =[1]本体装備品一覧!$AG$27 -> 0 | FI133: =[1]本体装備品一覧!$AN$27 -> 0
FB134: 1 | FC134: 22 | FD134: =[1]本体装備品一覧!$C$28 -> 0 | FE134: =[1]本体装備品一覧!$U$28 -> 0 | FF134: =[1]本体装備品一覧!$Y$28 -> 0 | FG134: =[1]本体装備品一覧!$AB$28 -> 0 | FH134: =[1]本体装備品一覧!$AG$28 -> 0 | FI134: =[1]本体装備品一覧!$AN$28 -> 0
FB135: 1 | FC135: 23 | FD135: =[1]本体装備品一覧!$C$29 -> 0 | FE135: =[1]本体装備品一覧!$U$29 -> 0 | FF135: =[1]本体装備品一覧!$Y$29 -> 0 | FG135: =[1]本体装備品一覧!$AB$29 -> 0 | FH135: =[1]本体装備品一覧!$AG$29 -> 0 | FI135: =[1]本体装備品一覧!$AN$29 -> 0
FB136: 2 | FC136: 1 | FD136: =#REF! -> #REF! | FE136: =#REF! -> #REF! | FF136: =#REF! -> #REF! | FG136: =#REF! -> #REF! | FH136: =#REF! -> #REF! | FI136: =#REF! -> #REF!
FB137: 2 | FC137: 2 | FD137: =#REF! -> #REF! | FE137: =#REF! -> #REF! | FF137: =#REF! -> #REF! | FG137: =#REF! -> #REF! | FH137: =#REF! -> #REF! | FI137: =#REF! -> #REF!
FB138: 2 | FC138: 3 | FD138: =#REF! -> #REF! | FE138: =#REF! -> #REF! | FF138: =#REF! -> #REF! | FG138: =#REF! -> #REF! | FH138: =#REF! -> #REF! | FI138: =#REF! -> #REF!
FB139: 2 | FC139: 4 | FD139: =#REF! -> #REF! | FE139: =#REF! -> #REF! | FF139: =#REF! -> #REF! | FG139: =#REF! -> #REF! | FH139: =#REF! -> #REF! | FI139: =#REF! -> #REF!
FB140: 2 | FC140: 5 | FD140: =#REF! -> #REF! | FE140: =#REF! -> #REF! | FF140: =#REF! -> #REF! | FG140: =#REF! -> #REF! | FH140: =#REF! -> #REF! | FI140: =#REF! -> #REF!
FB141: 2 | FC141: 6 | FD141: =#REF! -> #REF! | FE141: =#REF! -> #REF! | FF141: =#REF! -> #REF! | FG141: =#REF! -> #REF! | FH141: =#REF! -> #REF! | FI141: =#REF! -> #REF!
FB142: 2 | FC142: 7 | FD142: =#REF! -> #REF! | FE142: =#REF! -> #REF! | FF142: =#REF! -> #REF! | FG142: =#REF! -> #REF! | FH142: =#REF! -> #REF! | FI142: =#REF! -> #REF!
FB143: 2 | FC143: 8 | FD143: =#REF! -> #REF! | FE143: =#REF! -> #REF! | FF143: =#REF! -> #REF! | FG143: =#REF! -> #REF! | FH143: =#REF! -> #REF! | FI143: =#REF! -> #REF!
FB144: 2 | FC144: 9 | FD144: =#REF! -> #REF! | FE144: =#REF! -> #REF! | FF144: =#REF! -> #REF! | FG144: =#REF! -> #REF! | FH144: =#REF! -> #REF! | FI144: =#REF! -> #REF!
FB145: 2 | FC145: 10 | FD145: =#REF! -> #REF! | FE145: =#REF! -> #REF! | FF145: =#REF! -> #REF! | FG145: =#REF! -> #REF! | FH145: =#REF! -> #REF! | FI145: =#REF! -> #REF!
FB146: 2 | FC146: 11 | FD146: =#REF! -> #REF! | FE146: =#REF! -> #REF! | FF146: =#REF! -> #REF! | FG146: =#REF! -> #REF! | FH146: =#REF! -> #REF! | FI146: =#REF! -> #REF!
FB147: 2 | FC147: 12 | FD147: =#REF! -> #REF! | FE147: =#REF! -> #REF! | FF147: =#REF! -> #REF! | FG147: =#REF! -> #REF! | FH147: =#REF! -> #REF! | FI147: =#REF! -> #REF!
... FB173: 3 | FC173: 15 | FD173: =#REF! -> #REF! | FE173: =#REF! -> #REF! | FF173: =#REF! -> #REF! | FG173: =#REF! -> #REF! | FH173: =#REF! -> #REF! | FI173: =#REF! -> #REF!
P174: 0 | Q174: 15 | R174: 32 | S174: 117 | T174: 41 | U174: 124 | FB174: 3 | FC174: 16 | FD174: =#REF! -> #REF! | FE174: =#REF! -> #REF! | FF174: =#REF! -> #REF! | FG174: =#REF! -> #REF! | FH174: =#REF! -> #REF! | FI174: =#REF! -> #REF!
FB175: 3 | FC175: 17 | FD175: =#REF! -> #REF! | FE175: =#REF! -> #REF! | FF175: =#REF! -> #REF! | FG175: =#REF! -> #REF! | FH175: =#REF! -> #REF! | FI175: =#REF! -> #REF!
P176: 00-F-20-75-29-7C | FB176: 3 | FC176: 18 | FD176: =#REF! -> #REF! | FE176: =#REF! -> #REF! | FF176: =#REF! -> #REF! | FG176: =#REF! -> #REF! | FH176: =#REF! -> #REF! | FI176: =#REF! -> #REF!
FB177: 3 | FC177: 19 | FD177: =#REF! -> #REF! | FE177: =#REF! -> #REF! | FF177: =#REF! -> #REF! | FG177: =#REF! -> #REF! | FH177: =#REF! -> #REF! | FI177: =#REF! -> #REF!
FB178: 3 | FC178: 20 | FD178: =#REF! -> #REF! | FE178: =#REF! -> #REF! | FF178: =#REF! -> #REF! | FG178: =#REF! -> #REF! | FH178: =#REF! -> #REF! | FI178: =#REF! -> #REF!
FB179: 3 | FC179: 21 | FD179: =#REF! -> #REF! | FE179: =#REF! -> #REF! | FF179: =#REF! -> #REF! | FG179: =#REF! -> #REF! | FH179: =#REF! -> #REF! | FI179: =#REF! -> #REF!
FB180: 3 | FC180: 22 | FD180: =#REF! -> #REF! | FE180: =#REF! -> #REF! | FF180: =#REF! -> #REF! | FG180: =#REF! -> #REF! | FH180: =#REF! -> #REF! | FI180: =#REF! -> #REF!
FB181: 3 | FC181: 23 | FD181: =#REF! -> #REF! | FE181: =#REF! -> #REF! | FF181: =#REF! -> #REF! | FG181: =#REF! -> #REF! | FH181: =#REF! -> #REF! | FI181: =#REF! -> #REF!
FB400: NO | FC400: 明細NO | FD400: 品名 | FE400: 数量 | FF400: 単位 | FG400: 単価 | FH400: 金額 | FI400: 備考
