Workbook

Sheet 見積書A4
M2: CODE | AA2: 御 見 積 書
E3: 160-8511 | AL3: No. | AN3: FL2412245
D4: 東京都新宿区四谷4-1
AG6: 令和 | AI6: 6 | AL6: 年 | AM6: 12 | AO6: 月 | AP6: 24 | AR6: 日
D7: 大塚刷毛製造株式会社 | T7: 様
D11: 受渡期日 | H11: 14日～機種により
D13: 受渡場所 | H13: 貴社指定場所 | AB13: 振込先： | AE13: 十六銀行 柳ヶ瀬支店 普通：0777577
D15: 現金支払 | I15: 末締め末現金払い | AB15: 名義： | AE15: ｶ)ﾘﾝｼｭﾝﾄﾞｳ
AB17: 担当者 | AF17: 田中 健吾
J19: =H39 -> 165000
D20: 税込合計 | J20: =H39 -> 165000
B22: 見積書有効期限発効後1年
B24: 品 名 | T24: 数 量 | AA24: 税別単価 | AF24: 金 額 | AM24: 備 考
B26: RSD-SUNMAX-FL-LCW 1500w | X26: 一式 | AF26: =IF(T26="",1*AA26,T26*AA26) -> 0
B27: 設置操作講習費 日時：2025年4月12日（土曜） | X27: 一式 | AA27: 150000 | AF27: =IF(T27="",1*AA27,T27*AA27) -> 150000 | AM27: 10:00～17:00
AF28: =IF(T28="",1*AA28,T28*AA28) -> 0
B29: デモ機持ち込み費用除く | AF29: =IF(T29="",1*AA29,T29*AA29) -> 0
AF30: =IF(T30="",1*AA30,T30*AA30) -> 0
AF31: =IF(T31="",1*AA31,T31*AA31) -> 0
AF32: =IF(T32="",1*AA32,T32*AA32) -> 0
AF33: =IF(T33="",1*AA33,T33*AA33) -> 0
AF34: =IF(T34="",1*AA34,T34*AA34) -> 0
AF35: =IF(T35="",1*AA35,T35*AA35) -> 0
H38: =AA38*0.1 -> 15000 | T38: 小 計 | AA38: =SUM(AF26:AL37) -> 150000
B39: 合計金額 | H39: =CK115+H38 -> 165000
B40: 摘要： | E40: 場所 大塚刷毛製造株式会社 茨城営業所
B41: 〒300-0066 茨城県土浦市虫掛3545
P56: =SUM(CK115:CQ115) -> 150000
FB100: NO | FC100: 明細NO | FD100: 品名 | FE100: 数量 | FF100: 単位 | FG100: 単位 | FH100: 金額 | FI100: 備考
FB101: 0 | FC101: 1 | FD101: =B26 -> RSD-SUNMAX-FL-LCW 1500w | FE101: =T26 -> 0 | FF101: =X26 -> 一式 | FG101: =AA26 -> 0 | FH101: =AF26 -> 0 | FI101: =AM26 -> 0
EM102: ON | FB102: 0 | FC102: 2 | FD102: =B27 -> 設置操作講習費 日時：2025年4月12日（土曜） | FE102: =T27 -> 0 | FF102: =X27 -> 一式 | FG102: =AA27 -> 150000 | FH102: =AF27 -> 150000 | FI102: =AM27 -> 10:00～17:00
CE103: 制御 | CI103: 総計 | CS103: 単位 | CW103: 消費税 | DD103: タイトル | DM103: ﾏｽﾀﾊﾞｯｸｱｯﾌﾟ | EM103: OFF | FB103: 0 | FC103: 3 | FD103: =B28 -> 0 | FE103: =T28 -> 0 | FF103: =X28 -> 0 | FG103: =AA28 -> 0 | FH103: =AF28 -> 0 | FI103: =AM28 -> 0
CE104: 3 | CI104: 0 | CK104: =AA38 -> 150000 | CS104: 台 | CW104: 5 | CY104: ％ | DD104: 御 見 積 書 | DM104: ON | FB104: 0 | FC104: 4 | FD104: =B29 -> デモ機持ち込み費用除く | FE104: =T29 -> 0 | FF104: =X29 -> 0 | FG104: =AA29 -> 0 | FH104: =AF29 -> 0 | FI104: =AM29 -> 0
CE105: =MAX(FB401:FB642) -> 0 | CI105: 1 | CK105: =IF(ISERROR(本体装備品一覧!AB30),0,本体装備品一覧!AB30) -> 0 | CS105: 個 | DD105: 納 品 書 | FB105: 0 | FC105: 5 | FD105: =#REF! -> #REF! | FE105: =T30 -> 0 | FF105: =X30 -> 0 | FG105: =AA30 -> 0 | FH105: =AF30 -> 0 | FI105: =AM30 -> 0
CE106: 1 | CI106: 2 | CK106: =IF(ISERROR(#REF!),0,#REF!) -> 0 | CS106: 一式 | CV106: 画面表示 | DD106: 納 品 書 （控） | DM106: ﾃﾞｰﾀ保存ｼｰﾄ | FB106: 0 | FC106: 6 | FD106: =#REF! -> #REF! | FE106: =T31 -> 0 | FF106: =X31 -> 0 | FG106: =AA31 -> 0 | FH106: =AF31 -> 0 | FI106: =AM31 -> 0
CE107: 0 | CI107: 3 | CK107: =IF(ISERROR(#REF!),0,#REF!) -> 0 | CS107: 冊 | CV107: ① | CW107: 100 | CZ107: ％ | DD107: 請 求 書 | DM107: データ保存 1.xls | FB107: 0 | FC107: 7 | FD107: =#REF! -> #REF! | FE107: =T32 -> 0 | FF107: =X32 -> 0 | FG107: =AA32 -> 0 | FH107: =AF32 -> 0 | FI107: =AM32 -> 0
CE108: 敬称 | CI108: 4 | CS108: 箱 | CV108: ② | CW108: 80 | CZ108: ％ | DD108: 請 求 書 （控） | DM108: 鑑 | FB108: 0 | FC108: 8 | FD108: =B31 -> 0 | FE108: =T33 -> 0 | FF108: =X33 -> 0 | FG108: =AA33 -> 0 | FH108: =AF33 -> 0 | FI108: =AM33 -> 0
CE109: 御中 | CI109: 5 | CS109: C/S | DM109: 明細 | FB109: 0 | FC109: 9 | FD109: =B34 -> 0 | FE109: =T34 -> 0 | FF109: =X34 -> 0 | FG109: =AA34 -> 0 | FH109: =AF34 -> 0 | FI109: =AM34 -> 0
CE110: 様 | CI110: 6 | CS110: SET | CV110: 画像ファイル名 | DE110: 画像名 | FB110: 0 | FC110: 10 | FD110: =B35 -> 0 | FE110: =T35 -> 0 | FF110: =X35 -> 0 | FG110: =AA35 -> 0 | FH110: =AF35 -> 0 | FI110: =AM35 -> 0
CE111: 殿 | CI111: 7 | CS111: 本 | CV111: ① | CW111: 会社角印.gif | DE111: 会社角印 | FB111: 0 | FC111: 11 | FD111: =B36 -> 0 | FE111: =T36 -> 0 | FF111: =X36 -> 0 | FG111: =AA36 -> 0 | FH111: =AF36 -> 0 | FI111: =AM36 -> 0
CI112: 8 | CS112: 束 | CV112: ② | CW112: 林印.png | DE112: 林印 | FB112: 0 | FC112: 12 | FD112: =B37 -> 0 | FE112: =T37 -> 0 | FF112: =X37 -> 0 | FG112: =AA37 -> 0 | FH112: =AF37 -> 0 | FI112: =AM37 -> 0
CI113: 9 | CS113: 枚 | CV113: ③ | CW113: 佐藤.png | DE113: 佐藤印 | FB113: 1 | FC113: 1 | FD113: =本体装備品一覧!$C$7 -> 0 | FE113: =本体装備品一覧!$U$7 -> 0 | FF113: =本体装備品一覧!$Y$7 -> 0 | FG113: =本体装備品一覧!$AB$7 -> 0 | FH113: =本体装備品一覧!$AG$7 -> 0 | FI113: =本体装備品一覧!$AN$7 -> 0
CI114: 10 | CS114: ﾊﾟｯｸ | CV114: ④ | CW114: 青木印.gif | DE114: 青木印 | FB114: 1 | FC114: 2 | FD114: =本体装備品一覧!$C$8 -> 0 | FE114: =本体装備品一覧!$U$8 -> 0 | FF114: =本体装備品一覧!$Y$8 -> 0 | FG114: =本体装備品一覧!$AB$8 -> 0 | FH114: =本体装備品一覧!$AG$8 -> 0 | FI114: =本体装備品一覧!$AN$8 -> 0
CI115: 計 | CK115: =SUM(CK104:CQ114) -> 150000 | CS115: ｷｯﾄ | CV115: ⑤ | CW115: 中田印.gif | DE115: 中田印 | FB115: 1 | FC115: 3 | FD115: =本体装備品一覧!$C$9 -> 0 | FE115: =本体装備品一覧!$U$9 -> 0 | FF115: =本体装備品一覧!$Y$9 -> 0 | FG115: =本体装備品一覧!$AB$9 -> 0 | FH115: =本体装備品一覧!$AG$9 -> 0 | FI115: =本体装備品一覧!$AN$9 -> 0
FB116: 1 | FC116: 4 | FD116: =本体装備品一覧!$C$10 -> 0 | FE116: =本体装備品一覧!$U$10 -> 0 | FF116: =本体装備品一覧!$Y$10 -> 0 | FG116: =本体装備品一覧!$AB$10 -> 0 | FH116: =本体装備品一覧!$AG$10 -> 0 | FI116: =本体装備品一覧!$AN$10 -> 0
FB117: 1 | FC117: 5 | FD117: =本体装備品一覧!$C$11 -> 0 | FE117: =本体装備品一覧!$U$11 -> 0 | FF117: =本体装備品一覧!$Y$11 -> 0 | FG117: =本体装備品一覧!$AB$11 -> 0 | FH117: =本体装備品一覧!$AG$11 -> 0 | FI117: =本体装備品一覧!$AN$11 -> 0
FB118: 1 | FC118: 6 | FD118: =本体装備品一覧!$C$12 -> 0 | FE118: =本体装備品一覧!$U$12 -> 0 | FF118: =本体装備品一覧!$Y$12 -> 0 | FG118: =本体装備品一覧!$AB$12 -> 0 | FH118: =本体装備品一覧!$AG$12 -> 0 | FI118: =本体装備品一覧!$AN$12 -> 0
CI119: マスタパス | CM119: C:\Documents and Settings\sato\My Documents\シンプル見積書\ | DM119: ﾏｽﾀ | DO119: マスタ 1.xls | FB119: 1 | FC119: 7 | FD119: =本体装備品一覧!$C$13 -> 0 | FE119: =本体装備品一覧!$U$13 -> 0 | FF119: =本体装備品一覧!$Y$13 -> 0 | FG119: =本体装備品一覧!$AB$13 -> 0 | FH119: =本体装備品一覧!$AG$13 -> 0 | FI119: =本体装備品一覧!$AN$13 -> 0
CI120: データﾊﾟｽ | FB120: 1 | FC120: 8 | FD120: =本体装備品一覧!$C$14 -> 0 | FE120: =本体装備品一覧!$U$14 -> 0 | FF120: =本体装備品一覧!$Y$14 -> 0 | FG120: =本体装備品一覧!$AB$14 -> 0 | FH120: =本体装備品一覧!$AG$14 -> 0 | FI120: =本体装備品一覧!$AN$14 -> 0
FB121: 1 | FC121: 9 | FD121: =本体装備品一覧!$C$15 -> 0 | FE121: =本体装備品一覧!$U$15 -> 0 | FF121: =本体装備品一覧!$Y$15 -> 0 | FG121: =本体装備品一覧!$AB$15 -> 0 | FH121: =本体装備品一覧!$AG$15 -> 0 | FI121: =本体装備品一覧!$AN$15 -> 0
FB122: 1 | FC122: 10 | FD122: =本体装備品一覧!$C$16 -> 0 | FE122: =本体装備品一覧!$U$16 -> 0 | FF122: =本体装備品一覧!$Y$16 -> 0 | FG122: =本体装備品一覧!$AB$16 -> 0 | FH122: =本体装備品一覧!$AG$16 -> 0 | FI122: =本体装備品一覧!$AN$16 -> 0
FB123: 1 | FC123: 11 | FD123: =本体装備品一覧!$C$17 -> 0 | FE123: =本体装備品一覧!$U$17 -> 0 | FF123: =本体装備品一覧!$Y$17 -> 0 | FG123: =本体装備品一覧!$AB$17 -> 0 | FH123: =本体装備品一覧!$AG$17 -> 0 | FI123: =本体装備品一覧!$AN$17 -> 0
FB124: 1 | FC124: 12 | FD124: =本体装備品一覧!$C$18 -> 0 | FE124: =本体装備品一覧!$U$18 -> 0 | FF124: =本体装備品一覧!$Y$18 -> 0 | FG124: =本体装備品一覧!$AB$18 -> 0 | FH124: =本体装備品一覧!$AG$18 -> 0 | FI124: =本体装備品一覧!$AN$18 -> 0
FB125: 1 | FC125: 13 | FD125: =本体装備品一覧!$C$19 -> 0 | FE125: =本体装備品一覧!$U$19 -> 0 | FF125: =本体装備品一覧!$Y$19 -> 0 | FG125: =本体装備品一覧!$AB$19 -> 0 | FH125: =本体装備品一覧!$AG$19 -> 0 | FI125: =本体装備品一覧!$AN$19 -> 0
FB126: 1 | FC126: 14 | FD126: =本体装備品一覧!$C$20 -> 0 | FE126: =本体装備品一覧!$U$20 -> 0 | FF126: =本体装備品一覧!$Y$20 -> 0 | FG126: =本体装備品一覧!$AB$20 -> 0 | FH126: =本体装備品一覧!$AG$20 -> 0 | FI126: =本体装備品一覧!$AN$20 -> 0
FB127: 1 | FC127: 15 | FD127: =本体装備品一覧!$C$21 -> 0 | FE127: =本体装備品一覧!$U$21 -> 0 | FF127: =本体装備品一覧!$Y$21 -> 0 | FG127: =本体装備品一覧!$AB$21 -> 0 | FH127: =本体装備品一覧!$AG$21 -> 0 | FI127: =本体装備品一覧!$AN$21 -> 0
FB128: 1 | FC128: 16 | FD128: =本体装備品一覧!$C$22 -> 0 | FE128: =本体装備品一覧!$U$22 -> 0 | FF128: =本体装備品一覧!$Y$22 -> 0 | FG128: =本体装備品一覧!$AB$22 -> 0 | FH128: =本体装備品一覧!$AG$22 -> 0 | FI128: =本体装備品一覧!$AN$22 -> 0
FB129: 1 | FC129: 17 | FD129: =本体装備品一覧!$C$23 -> 0 | FE129: =本体装備品一覧!$U$23 -> 0 | FF129: =本体装備品一覧!$Y$23 -> 0 | FG129: =本体装備品一覧!$AB$23 -> 0 | FH129: =本体装備品一覧!$AG$23 -> 0 | FI129: =本体装備品一覧!$AN$23 -> 0
FB130: 1 | FC130: 18 | FD130: =本体装備品一覧!$C$24 -> 0 | FE130: =本体装備品一覧!$U$24 -> 0 | FF130: =本体装備品一覧!$Y$24 -> 0 | FG130: =本体装備品一覧!$AB$24 -> 0 | FH130: =本体装備品一覧!$AG$24 -> 0 | FI130: =本体装備品一覧!$AN$24 -> 0
FB131: 1 | FC131: 19 | FD131: =本体装備品一覧!$C$25 -> 0 | FE131: =本体装備品一覧!$U$25 -> 0 | FF131: =本体装備品一覧!$Y$25 -> 0 | FG131: =本体装備品一覧!$AB$25 -> 0 | FH131: =本体装備品一覧!$AG$25 -> 0 | FI131: =本体装備品一覧!$AN$25 -> 0
FB132: 1 | FC132: 20 | FD132: =本体装備品一覧!$C$26 -> 0 | FE132: =本体装備品一覧!$U$26 -> 0 | FF132: =本体装備品一覧!$Y$26 -> 0 | FG132: =本体装備品一覧!$AB$26 -> 0 | FH132: =本体装備品一覧!$AG$26 -> 0 | FI132: =本体装備品一覧!$AN$26 -> 0
FB133: 1 | FC133: 21 | FD133: =本体装備品一覧!$C$27 -> 0 | FE133: =本体装備品一覧!$U$27 -> 0 | FF133: =本体装備品一覧!$Y$27 -> 0 | FG133: =本体装備品一覧!$AB$27 -> 0 | FH133: =本体装備品一覧!$AG$27 -> 0 | FI133: =本体装備品一覧!$AN$27 -> 0
FB134: 1 | FC134: 22 | FD134: =本体装備品一覧!$C$28 -> 0 | FE134: =本体装備品一覧!$U$28 -> 0 | FF134: =本体装備品一覧!$Y$28 -> 0 | FG134: =本体装備品一覧!$AB$28 -> 0 | FH134: =本体装備品一覧!$AG$28 -> 0 | FI134: =本体装備品一覧!$AN$28 -> 0
FB135: 1 | FC135: 23 | FD135: =本体装備品一覧!$C$29 -> 0 | FE135: =本体装備品一覧!$U$29 -> 0 | FF135: =本体装備品一覧!$Y$29 -> 0 | FG135: =本体装備品一覧!$AB$29 -> 0 | FH135: =本体装備品一覧!$AG$29 -> 0 | FI135: =本体装備品一覧!$AN$29 -> 0
FB136: 2 | FC136: 1 | FD136: =#REF! -> #REF! | FE136: =#REF! -> #REF! | FF136: =#REF! -> #REF! | FG136: =#REF! -> #REF! | FH136: =#REF! -> #REF! | FI136: =#REF! -> #REF!
FB137: 2 | FC137: 2 | FD137: =#REF! -> #REF! | FE137: =#REF! -> #REF! | FF137: =#REF! -> #REF! | FG137: =#REF! -> #REF! | FH137: =#REF! -> #REF! | FI137: =#REF! -> #REF!
FB138: 2 | FC138: 3 | FD138: =#REF! -> #REF! | FE138: =#REF! -> #REF! | FF138: =#REF! -> #REF! | FG138: =#REF! -> #REF! | FH138: =#REF! -> #REF! | FI138: =#REF! -> #REF!
FB139: 2 | FC139: 4 | FD139: =#REF! -> #REF! | FE139: =#REF! -> #REF! | FF139: =#REF! -> #REF! | FG139: =#REF! -> #REF! | FH139: =#REF! -> #REF! | FI139: =#REF! -> #REF!
FB140: 2 | FC140: 5 | FD140: =#REF! -> #REF! | FE140: =#REF! -> #REF! | FF140: =#REF! -> #REF! | FG140: =#REF! -> #REF! | FH140: =#REF! -> #REF! | FI140: =#REF! -> #REF!
FB141: 2 | FC141: 6 | FD141: =#REF! -> #REF! | FE141: =#REF! -> #REF! | FF141: =#REF! -> #REF! | FG141: =#REF! -> #REF! | FH141: =#REF! -> #REF! | FI141: =#REF! -> #REF!
FB142: 2 | FC142: 7 | FD142: =#REF! -> #REF! | FE142: =#REF! -> #REF! | FF142: =#REF! -> #REF! | FG142: =#REF! -> #REF! | FH142: =#REF! -> #REF! | FI142: =#REF! -> #REF!
FB143: 2 | FC143: 8 | FD143: =#REF! -> #REF! | FE143: =#REF! -> #REF! | FF143: =#REF! -> #REF! | FG143: =#REF! -> #REF! | FH143: =#REF! -> #REF! | FI143: =#REF! -> #REF!
FB144: 2 | FC144: 9 | FD144: =#REF! -> #REF! | FE144: =#REF! -> #REF! | FF144: =#REF! -> #REF! | FG144: =#REF! -> #REF! | FH144: =#REF! -> #REF! | FI144: =#REF! -> #REF!
FB145: 2 | FC145: 10 | FD145: =#REF! -> #REF! | FE145: =#REF! -> #REF! | FF145: =#REF! -> #REF! | FG145: =#REF! -> #REF! | FH145: =#REF! -> #REF! | FI145: =#REF! -> #REF!
FB146: 2 | FC146: 11 | FD146: =#REF! -> #REF! | FE146: =#REF! -> #REF! | FF146: =#REF! -> #REF! | FG146: =#REF! -> #REF! | FH146: =#REF! -> #REF! | FI146: =#REF! -> #REF!
FB147: 2 | FC147: 12 | FD147: =#REF! -> #REF! | FE147: =#REF! -> #REF! | FF147: =#REF! -> #REF! | FG147: =#REF! -> #REF! | FH147: =#REF! -> #REF! | FI147: =#REF! -> #REF!
... FB173: 3 | FC173: 15 | FD173: =#REF! -> #REF! | FE173: =#REF! -> #REF! | FF173: =#REF! -> #REF! | FG173: =#REF! -> #REF! | FH173: =#REF! -> #REF! | FI173: =#REF! -> #REF!
P174: 0 | Q174: 15 | R174: 32 | S174: 117 | T174: 41 | U174: 124 | FB174: 3 | FC174: 16 | FD174: =#REF! -> #REF! | FE174: =#REF! -> #REF! | FF174: =#REF! -> #REF! | FG174: =#REF! -> #REF! | FH174: =#REF! -> #REF! | FI174: =#REF! -> #REF!
FB175: 3 | FC175: 17 | FD175: =#REF! -> #REF! | FE175: =#REF! -> #REF! | FF175: =#REF! -> #REF! | FG175: =#REF! -> #REF! | FH175: =#REF! -> #REF! | FI175: =#REF! -> #REF!
P176: 00-F-20-75-29-7C | FB176: 3 | FC176: 18 | FD176: =#REF! -> #REF! | FE176: =#REF! -> #REF! | FF176: =#REF! -> #REF! | FG176: =#REF! -> #REF! | FH176: =#REF! -> #REF! | FI176: =#REF! -> #REF!
FB177: 3 | FC177: 19 | FD177: =#REF! -> #REF! | FE177: =#REF! -> #REF! | FF177: =#REF! -> #REF! | FG177: =#REF! -> #REF! | FH177: =#REF! -> #REF! | FI177: =#REF! -> #REF!
FB178: 3 | FC178: 20 | FD178: =#REF! -> #REF! | FE178: =#REF! -> #REF! | FF178: =#REF! -> #REF! | FG178: =#REF! -> #REF! | FH178: =#REF! -> #REF! | FI178: =#REF! -> #REF!
FB179: 3 | FC179: 21 | FD179: =#REF! -> #REF! | FE179: =#REF! -> #REF! | FF179: =#REF! -> #REF! | FG179: =#REF! -> #REF! | FH179: =#REF! -> #REF! | FI179: =#REF! -> #REF!
FB180: 3 | FC180: 22 | FD180: =#REF! -> #REF! | FE180: =#REF! -> #REF! | FF180: =#REF! -> #REF! | FG180: =#REF! -> #REF! | FH180: =#REF! -> #REF! | FI180: =#REF! -> #REF!
FB181: 3 | FC181: 23 | FD181: =#REF! -> #REF! | FE181: =#REF! -> #REF! | FF181: =#REF! -> #REF! | FG181: =#REF! -> #REF! | FH181: =#REF! -> #REF! | FI181: =#REF! -> #REF!
FB400: NO | FC400: 明細NO | FD400: 品名 | FE400: 数量 | FF400: 単位 | FG400: 単価 | FH400: 金額 | FI400: 備考

Sheet 請求書
M2: CODE | AA2: 請 求 書
E3: 160-8511 | AL3: No. | AN3: FL2504145
D4: 東京都新宿区四谷4-1
AG6: 令和 | AI6: 7 | AL6: 年 | AM6: 4 | AO6: 月 | AP6: 14 | AR6: 日
D7: 大塚刷毛製造株式会社 | T7: 様
D11: 受渡期日 | H11: 45759
D13: 受渡場所 | H13: 茨城営業所 | AB13: 振込先： | AE13: 十六銀行 柳ヶ瀬支店 普通：0777577
D15: 現金支払 | I15: 末締め末現金払い | AB15: 名義： | AE15: ｶ)ﾘﾝｼｭﾝﾄﾞｳ
AB17: 担当者 | AF17: 田中 健吾
J19: =H39 -> 165000
D20: 税込合計 | J20: =H39 -> 165000
B22: 見積書有効期限発効後1年
B24: 品 名 | T24: 数 量 | AA24: 税別単価 | AF24: 金 額 | AM24: 備 考
B26: RSD-SUNMAX-FL-LCW 1500w | X26: 一式 | AF26: =IF(T26="",1*AA26,T26*AA26) -> 0
B27: 設置操作講習費 日時：2025年4月12日（土曜） | X27: 一式 | AA27: 150000 | AF27: =IF(T27="",1*AA27,T27*AA27) -> 150000 | AM27: 10:00～17:00
AF28: =IF(T28="",1*AA28,T28*AA28) -> 0
B29: デモ機持ち込み費用除く | AF29: =IF(T29="",1*AA29,T29*AA29) -> 0
AF30: =IF(T30="",1*AA30,T30*AA30) -> 0
AF31: =IF(T31="",1*AA31,T31*AA31) -> 0
AF32: =IF(T32="",1*AA32,T32*AA32) -> 0
AF33: =IF(T33="",1*AA33,T33*AA33) -> 0
AF34: =IF(T34="",1*AA34,T34*AA34) -> 0
AF35: =IF(T35="",1*AA35,T35*AA35) -> 0
H38: =AA38*0.1 -> 15000 | T38: 小 計 | AA38: =SUM(AF26:AL37) -> 150000
B39: 合計金額 | H39: =CK115+H38 -> 165000
B40: 摘要： | E40: 場所 大塚刷毛製造株式会社 茨城営業所
B41: 〒300-0066 茨城県土浦市虫掛3545
P56: =SUM(CK115:CQ115) -> 150000
FB100: NO | FC100: 明細NO | FD100: 品名 | FE100: 数量 | FF100: 単位 | FG100: 単位 | FH100: 金額 | FI100: 備考
FB101: 0 | FC101: 1 | FD101: =B26 -> RSD-SUNMAX-FL-LCW 1500w | FE101: =T26 -> 0 | FF101: =X26 -> 一式 | FG101: =AA26 -> 0 | FH101: =AF26 -> 0 | FI101: =AM26 -> 0
EM102: ON | FB102: 0 | FC102: 2 | FD102: =B27 -> 設置操作講習費 日時：2025年4月12日（土曜） | FE102: =T27 -> 0 | FF102: =X27 -> 一式 | FG102: =AA27 -> 150000 | FH102: =AF27 -> 150000 | FI102: =AM27 -> 10:00～17:00
CE103: 制御 | CI103: 総計 | CS103: 単位 | CW103: 消費税 | DD103: タイトル | DM103: ﾏｽﾀﾊﾞｯｸｱｯﾌﾟ | EM103: OFF | FB103: 0 | FC103: 3 | FD103: =B28 -> 0 | FE103: =T28 -> 0 | FF103: =X28 -> 0 | FG103: =AA28 -> 0 | FH103: =AF28 -> 0 | FI103: =AM28 -> 0
CE104: 3 | CI104: 0 | CK104: =AA38 -> 150000 | CS104: 台 | CW104: 5 | CY104: ％ | DD104: 御 見 積 書 | DM104: ON | FB104: 0 | FC104: 4 | FD104: =B29 -> デモ機持ち込み費用除く | FE104: =T29 -> 0 | FF104: =X29 -> 0 | FG104: =AA29 -> 0 | FH104: =AF29 -> 0 | FI104: =AM29 -> 0
CE105: =MAX(FB401:FB642) -> 0 | CI105: 1 | CK105: =IF(ISERROR(本体装備品一覧!AB30),0,本体装備品一覧!AB30) -> 0 | CS105: 個 | DD105: 納 品 書 | FB105: 0 | FC105: 5 | FD105: =#REF! -> #REF! | FE105: =T30 -> 0 | FF105: =X30 -> 0 | FG105: =AA30 -> 0 | FH105: =AF30 -> 0 | FI105: =AM30 -> 0
CE106: 1 | CI106: 2 | CK106: =IF(ISERROR(#REF!),0,#REF!) -> 0 | CS106: 一式 | CV106: 画面表示 | DD106: 納 品 書 （控） | DM106: ﾃﾞｰﾀ保存ｼｰﾄ | FB106: 0 | FC106: 6 | FD106: =#REF! -> #REF! | FE106: =T31 -> 0 | FF106: =X31 -> 0 | FG106: =AA31 -> 0 | FH106: =AF31 -> 0 | FI106: =AM31 -> 0
CE107: 0 | CI107: 3 | CK107: =IF(ISERROR(#REF!),0,#REF!) -> 0 | CS107: 冊 | CV107: ① | CW107: 100 | CZ107: ％ | DD107: 請 求 書 | DM107: データ保存 1.xls | FB107: 0 | FC107: 7 | FD107: =#REF! -> #REF! | FE107: =T32 -> 0 | FF107: =X32 -> 0 | FG107: =AA32 -> 0 | FH107: =AF32 -> 0 | FI107: =AM32 -> 0
CE108: 敬称 | CI108: 4 | CS108: 箱 | CV108: ② | CW108: 80 | CZ108: ％ | DD108: 請 求 書 （控） | DM108: 鑑 | FB108: 0 | FC108: 8 | FD108: =B31 -> 0 | FE108: =T33 -> 0 | FF108: =X33 -> 0 | FG108: =AA33 -> 0 | FH108: =AF33 -> 0 | FI108: =AM33 -> 0
CE109: 御中 | CI109: 5 | CS109: C/S | DM109: 明細 | FB109: 0 | FC109: 9 | FD109: =B34 -> 0 | FE109: =T34 -> 0 | FF109: =X34 -> 0 | FG109: =AA34 -> 0 | FH109: =AF34 -> 0 | FI109: =AM34 -> 0
CE110: 様 | CI110: 6 | CS110: SET | CV110: 画像ファイル名 | DE110: 画像名 | FB110: 0 | FC110: 10 | FD110: =B35 -> 0 | FE110: =T35 -> 0 | FF110: =X35 -> 0 | FG110: =AA35 -> 0 | FH110: =AF35 -> 0 | FI110: =AM35 -> 0
CE111: 殿 | CI111: 7 | CS111: 本 | CV111: ① | CW111: 会社角印.gif | DE111: 会社角印 | FB111: 0 | FC111: 11 | FD111: =B36 -> 0 | FE111: =T36 -> 0 | FF111: =X36 -> 0 | FG111: =AA36 -> 0 | FH111: =AF36 -> 0 | FI111: =AM36 -> 0
CI112: 8 | CS112: 束 | CV112: ② | CW112: 林印.png | DE112: 林印 | FB112: 0 | FC112: 12 | FD112: =B37 -> 0 | FE112: =T37 -> 0 | FF112: =X37 -> 0 | FG112: =AA37 -> 0 | FH112: =AF37 -> 0 | FI112: =AM37 -> 0
CI113: 9 | CS113: 枚 | CV113: ③ | CW113: 佐藤.png | DE113: 佐藤印 | FB113: 1 | FC113: 1 | FD113: =本体装備品一覧!$C$7 -> 0 | FE113: =本体装備品一覧!$U$7 -> 0 | FF113: =本体装備品一覧!$Y$7 -> 0 | FG113: =本体装備品一覧!$AB$7 -> 0 | FH113: =本体装備品一覧!$AG$7 -> 0 | FI113: =本体装備品一覧!$AN$7 -> 0
CI114: 10 | CS114: ﾊﾟｯｸ | CV114: ④ | CW114: 青木印.gif | DE114: 青木印 | FB114: 1 | FC114: 2 | FD114: =本体装備品一覧!$C$8 -> 0 | FE114: =本体装備品一覧!$U$8 -> 0 | FF114: =本体装備品一覧!$Y$8 -> 0 | FG114: =本体装備品一覧!$AB$8 -> 0 | FH114: =本体装備品一覧!$AG$8 -> 0 | FI114: =本体装備品一覧!$AN$8 -> 0
CI115: 計 | CK115: =SUM(CK104:CQ114) -> 150000 | CS115: ｷｯﾄ | CV115: ⑤ | CW115: 中田印.gif | DE115: 中田印 | FB115: 1 | FC115: 3 | FD115: =本体装備品一覧!$C$9 -> 0 | FE115: =本体装備品一覧!$U$9 -> 0 | FF115: =本体装備品一覧!$Y$9 -> 0 | FG115: =本体装備品一覧!$AB$9 -> 0 | FH115: =本体装備品一覧!$AG$9 -> 0 | FI115: =本体装備品一覧!$AN$9 -> 0
FB116: 1 | FC116: 4 | FD116: =本体装備品一覧!$C$10 -> 0 | FE116: =本体装備品一覧!$U$10 -> 0 | FF116: =本体装備品一覧!$Y$10 -> 0 | FG116: =本体装備品一覧!$AB$10 -> 0 | FH116: =本体装備品一覧!$AG$10 -> 0 | FI116: =本体装備品一覧!$AN$10 -> 0
FB117: 1 | FC117: 5 | FD117: =本体装備品一覧!$C$11 -> 0 | FE117: =本体装備品一覧!$U$11 -> 0 | FF117: =本体装備品一覧!$Y$11 -> 0 | FG117: =本体装備品一覧!$AB$11 -> 0 | FH117: =本体装備品一覧!$AG$11 -> 0 | FI117: =本体装備品一覧!$AN$11 -> 0
FB118: 1 | FC118: 6 | FD118: =本体装備品一覧!$C$12 -> 0 | FE118: =本体装備品一覧!$U$12 -> 0 | FF118: =本体装備品一覧!$Y$12 -> 0 | FG118: =本体装備品一覧!$AB$12 -> 0 | FH118: =本体装備品一覧!$AG$12 -> 0 | FI118: =本体装備品一覧!$AN$12 -> 0
CI119: マスタパス | CM119: C:\Documents and Settings\sato\My Documents\シンプル見積書\ | DM119: ﾏｽﾀ | DO119: マスタ 1.xls | FB119: 1 | FC119: 7 | FD119: =本体装備品一覧!$C$13 -> 0 | FE119: =本体装備品一覧!$U$13 -> 0 | FF119: =本体装備品一覧!$Y$13 -> 0 | FG119: =本体装備品一覧!$AB$13 -> 0 | FH119: =本体装備品一覧!$AG$13 -> 0 | FI119: =本体装備品一覧!$AN$13 -> 0
CI120: データﾊﾟｽ | FB120: 1 | FC120: 8 | FD120: =本体装備品一覧!$C$14 -> 0 | FE120: =本体装備品一覧!$U$14 -> 0 | FF120: =本体装備品一覧!$Y$14 -> 0 | FG120: =本体装備品一覧!$AB$14 -> 0 | FH120: =本体装備品一覧!$AG$14 -> 0 | FI120: =本体装備品一覧!$AN$14 -> 0
FB121: 1 | FC121: 9 | FD121: =本体装備品一覧!$C$15 -> 0 | FE121: =本体装備品一覧!$U$15 -> 0 | FF121: =本体装備品一覧!$Y$15 -> 0 | FG121: =本体装備品一覧!$AB$15 -> 0 | FH121: =本体装備品一覧!$AG$15 -> 0 | FI121: =本体装備品一覧!$AN$15 -> 0
FB122: 1 | FC122: 10 | FD122: =本体装備品一覧!$C$16 -> 0 | FE122: =本体装備品一覧!$U$16 -> 0 | FF122: =本体装備品一覧!$Y$16 -> 0 | FG122: =本体装備品一覧!$AB$16 -> 0 | FH122: =本体装備品一覧!$AG$16 -> 0 | FI122: =本体装備品一覧!$AN$16 -> 0
FB123: 1 | FC123: 11 | FD123: =本体装備品一覧!$C$17 -> 0 | FE123: =本体装備品一覧!$U$17 -> 0 | FF123: =本体装備品一覧!$Y$17 -> 0 | FG123: =本体装備品一覧!$AB$17 -> 0 | FH123: =本体装備品一覧!$AG$17 -> 0 | FI123: =本体装備品一覧!$AN$17 -> 0
FB124: 1 | FC124: 12 | FD124: =本体装備品一覧!$C$18 -> 0 | FE124: =本体装備品一覧!$U$18 -> 0 | FF124: =本体装備品一覧!$Y$18 -> 0 | FG124: =本体装備品一覧!$AB$18 -> 0 | FH124: =本体装備品一覧!$AG$18 -> 0 | FI124: =本体装備品一覧!$AN$18 -> 0
FB125: 1 | FC125: 13 | FD125: =本体装備品一覧!$C$19 -> 0 | FE125: =本体装備品一覧!$U$19 -> 0 | FF125: =本体装備品一覧!$Y$19 -> 0 | FG125: =本体装備品一覧!$AB$19 -> 0 | FH125: =本体装備品一覧!$AG$19 -> 0 | FI125: =本体装備品一覧!$AN$19 -> 0
FB126: 1 | FC126: 14 | FD126: =本体装備品一覧!$C$20 -> 0 | FE126: =本体装備品一覧!$U$20 -> 0 | FF126: =本体装備品一覧!$Y$20 -> 0 | FG126: =本体装備品一覧!$AB$20 -> 0 | FH126: =本体装備品一覧!$AG$20 -> 0 | FI126: =本体装備品一覧!$AN$20 -> 0
FB127: 1 | FC127: 15 | FD127: =本体装備品一覧!$C$21 -> 0 | FE127: =本体装備品一覧!$U$21 -> 0 | FF127: =本体装備品一覧!$Y$21 -> 0 | FG127: =本体装備品一覧!$AB$21 -> 0 | FH127: =本体装備品一覧!$AG$21 -> 0 | FI127: =本体装備品一覧!$AN$21 -> 0
FB128: 1 | FC128: 16 | FD128: =本体装備品一覧!$C$22 -> 0 | FE128: =本体装備品一覧!$U$22 -> 0 | FF128: =本体装備品一覧!$Y$22 -> 0 | FG128: =本体装備品一覧!$AB$22 -> 0 | FH128: =本体装備品一覧!$AG$22 -> 0 | FI128: =本体装備品一覧!$AN$22 -> 0
FB129: 1 | FC129: 17 | FD129: =本体装備品一覧!$C$23 -> 0 | FE129: =本体装備品一覧!$U$23 -> 0 | FF129: =本体装備品一覧!$Y$23 -> 0 | FG129: =本体装備品一覧!$AB$23 -> 0 | FH129: =本体装備品一覧!$AG$23 -> 0 | FI129: =本体装備品一覧!$AN$23 -> 0
FB130: 1 | FC130: 18 | FD130: =本体装備品一覧!$C$24 -> 0 | FE130: =本体装備品一覧!$U$24 -> 0 | FF130: =本体装備品一覧!$Y$24 -> 0 | FG130: =本体装備品一覧!$AB$24 -> 0 | FH130: =本体装備品一覧!$AG$24 -> 0 | FI130: =本体装備品一覧!$AN$24 -> 0
FB131: 1 | FC131: 19 | FD131: =本体装備品一覧!$C$25 -> 0 | FE131: =本体装備品一覧!$U$25 -> 0 | FF131: =本体装備品一覧!$Y$25 -> 0 | FG131: =本体装備品一覧!$AB$25 -> 0 | FH131: =本体装備品一覧!$AG$25 -> 0 | FI131: =本体装備品一覧!$AN$25 -> 0
FB132: 1 | FC132: 20 | FD132: =本体装備品一覧!$C$26 -> 0 | FE132: =本体装備品一覧!$U$26 -> 0 | FF132: =本体装備品一覧!$Y$26 -> 0 | FG132: =本体装備品一覧!$AB$26 -> 0 | FH132: =本体装備品一覧!$AG$26 -> 0 | FI132: =本体装備品一覧!$AN$26 -> 0
FB133: 1 | FC133: 21 | FD133: =本体装備品一覧!$C$27 -> 0 | FE133: =本体装備品一覧!$U$27 -> 0 | FF133: =本体装備品一覧!$Y$27 -> 0 | FG133: =本体装備品一覧!$AB$27 -> 0 | FH133: =本体装備品一覧!$AG$27 -> 0 | FI133: =本体装備品一覧!$AN$27 -> 0
FB134: 1 | FC134: 22 | FD134: =本体装備品一覧!$C$28 -> 0 | FE134: =本体装備品一覧!$U$28 -> 0 | FF134: =本体装備品一覧!$Y$28 -> 0 | FG134: =本体装備品一覧!$AB$28 -> 0 | FH134: =本体装備品一覧!$AG$28 -> 0 | FI134: =本体装備品一覧!$AN$28 -> 0
FB135: 1 | FC135: 23 | FD135: =本体装備品一覧!$C$29 -> 0 | FE135: =本体装備品一覧!$U$29 -> 0 | FF135: =本体装備品一覧!$Y$29 -> 0 | FG135: =本体装備品一覧!$AB$29 -> 0 | FH135: =本体装備品一覧!$AG$29 -> 0 | FI135: =本体装備品一覧!$AN$29 -> 0
FB136: 2 | FC136: 1 | FD136: =#REF! -> #REF! | FE136: =#REF! -> #REF! | FF136: =#REF! -> #REF! | FG136: =#REF! -> #REF! | FH136: =#REF! -> #REF! | FI136: =#REF! -> #REF!
FB137: 2 | FC137: 2 | FD137: =#REF! -> #REF! | FE137: =#REF! -> #REF! | FF137: =#REF! -> #REF! | FG137: =#REF! -> #REF! | FH137: =#REF! -> #REF! | FI137: =#REF! -> #REF!
FB138: 2 | FC138: 3 | FD138: =#REF! -> #REF! | FE138: =#REF! -> #REF! | FF138: =#REF! -> #REF! | FG138: =#REF! -> #REF! | FH138: =#REF! -> #REF! | FI138: =#REF! -> #REF!
FB139: 2 | FC139: 4 | FD139: =#REF! -> #REF! | FE139: =#REF! -> #REF! | FF139: =#REF! -> #REF! | FG139: =#REF! -> #REF! | FH139: =#REF! -> #REF! | FI139: =#REF! -> #REF!
FB140: 2 | FC140: 5 | FD140: =#REF! -> #REF! | FE140: =#REF! -> #REF! | FF140: =#REF! -> #REF! | FG140: =#REF! -> #REF! | FH140: =#REF! -> #REF! | FI140: =#REF! -> #REF!
FB141: 2 | FC141: 6 | FD141: =#REF! -> #REF! | FE141: =#REF! -> #REF! | FF141: =#REF! -> #REF! | FG141: =#REF! -> #REF! | FH141: =#REF! -> #REF! | FI141: =#REF! -> #REF!
FB142: 2 | FC142: 7 | FD142: =#REF! -> #REF! | FE142: =#REF! -> #REF! | FF142: =#REF! -> #REF! | FG142: =#REF! -> #REF! | FH142: =#REF! -> #REF! | FI142: =#REF! -> #REF!
FB143: 2 | FC143: 8 | FD143: =#REF! -> #REF! | FE143: =#REF! -> #REF! | FF143: =#REF! -> #REF! | FG143: =#REF! -> #REF! | FH143: =#REF! -> #REF! | FI143: =#REF! -> #REF!
FB144: 2 | FC144: 9 | FD144: =#REF! -> #REF! | FE144: =#REF! -> #REF! | FF144: =#REF! -> #REF! | FG144: =#REF! -> #REF! | FH144: =#REF! -> #REF! | FI144: =#REF! -> #REF!
FB145: 2 | FC145: 10 | FD145: =#REF! -> #REF! | FE145: =#REF! -> #REF! | FF145: =#REF! -> #REF! | FG145: =#REF! -> #REF! | FH145: =#REF! -> #REF! | FI145: =#REF! -> #REF!
FB146: 2 | FC146: 11 | FD146: =#REF! -> #REF! | FE146: =#REF! -> #REF! | FF146: =#REF! -> #REF! | FG146: =#REF! -> #REF! | FH146: =#REF! -> #REF! | FI146: =#REF! -> #REF!
FB147: 2 | FC147: 12 | FD147: =#REF! -> #REF! | FE147: =#REF! -> #REF! | FF147: =#REF! -> #REF! | FG147: =#REF! -> #REF! | FH147: =#REF! -> #REF! | FI147: =#REF! -> #REF!
... FB173: 3 | FC173: 15 | FD173: =#REF! -> #REF! | FE173: =#REF! -> #REF! | FF173: =#REF! -> #REF! | FG173: =#REF! -> #REF! | FH173: =#REF! -> #REF! | FI173: =#REF! -> #REF!
P174: 0 | Q174: 15 | R174: 32 | S174: 117 | T174: 41 | U174: 124 | FB174: 3 | FC174: 16 | FD174: =#REF! -> #REF! | FE174: =#REF! -> #REF! | FF174: =#REF! -> #REF! | FG174: =#REF! -> #REF! | FH174: =#REF! -> #REF! | FI174: =#REF! -> #REF!
FB175: 3 | FC175: 17 | FD175: =#REF! -> #REF! | FE175: =#REF! -> #REF! | FF175: =#REF! -> #REF! | FG175: =#REF! -> #REF! | FH175: =#REF! -> #REF! | FI175: =#REF! -> #REF!
P176: 00-F-20-75-29-7C | FB176: 3 | FC176: 18 | FD176: =#REF! -> #REF! | FE176: =#REF! -> #REF! | FF176: =#REF! -> #REF! | FG176: =#REF! -> #REF! | FH176: =#REF! -> #REF! | FI176: =#REF! -> #REF!
FB177: 3 | FC177: 19 | FD177: =#REF! -> #REF! | FE177: =#REF! -> #REF! | FF177: =#REF! -> #REF! | FG177: =#REF! -> #REF! | FH177: =#REF! -> #REF! | FI177: =#REF! -> #REF!
FB178: 3 | FC178: 20 | FD178: =#REF! -> #REF! | FE178: =#REF! -> #REF! | FF178: =#REF! -> #REF! | FG178: =#REF! -> #REF! | FH178: =#REF! -> #REF! | FI178: =#REF! -> #REF!
FB179: 3 | FC179: 21 | FD179: =#REF! -> #REF! | FE179: =#REF! -> #REF! | FF179: =#REF! -> #REF! | FG179: =#REF! -> #REF! | FH179: =#REF! -> #REF! | FI179: =#REF! -> #REF!
FB180: 3 | FC180: 22 | FD180: =#REF! -> #REF! | FE180: =#REF! -> #REF! | FF180: =#REF! -> #REF! | FG180: =#REF! -> #REF! | FH180: =#REF! -> #REF! | FI180: =#REF! -> #REF!
FB181: 3 | FC181: 23 | FD181: =#REF! -> #REF! | FE181: =#REF! -> #REF! | FF181: =#REF! -> #REF! | FG181: =#REF! -> #REF! | FH181: =#REF! -> #REF! | FI181: =#REF! -> #REF!
FB400: NO | FC400: 明細NO | FD400: 品名 | FE400: 数量 | FF400: 単位 | FG400: 単価 | FH400: 金額 | FI400: 備考

Sheet 別紙購入おすすめ品
D3: 別紙購入おすすめ品一覧 | AL3: No.
C5: 付 属 品 名 | U5: 数 量 | AB5: 単 価 | AG5: 金 額 | AN5: 備 考
C7: 反射レンズレンズ＋ステー | U7: 1 | Y7: 枚 | AB7: 13200 | AG7: =IF(U7="",1*AB7,U7*AB7) -> 13200
C8: コリメーターレンズ | U8: 1 | Y8: 枚 | AB8: 10340 | AG8: =IF(U8="",1*AB8,U8*AB8) -> 10340
C9: 溶接・切断用焦点レンズ【ケース付き】 | U9: 1 | Y9: 枚 | AB9: 18400 | AG9: =IF(U9="",1*AB9,U9*AB9) -> 18400
C10: 洗浄用焦点レンズ【ケース付き】 | U10: 1 | Y10: 枚 | AB10: 18400 | AG10: =IF(U10="",1*AB10,U10*AB10) -> 18400
C11: シールリング ※シールリングのみ | U11: 1 | Y11: 枚 | AB11: 3960 | AG11: =IF(U11="",1*AB11,U11*AB11) -> 3960
C12: 溶接・切断用 保護レンズ | U12: 10 | Y12: 枚 | AB12: 1200 | AG12: =IF(U12="",1*AB12,U12*AB12) -> 12000
AG13: =IF(U13="",1*AB13,U13*AB13) -> 0
AG14: =IF(U14="",1*AB14,U14*AB14) -> 0
AG15: =IF(U15="",1*AB15,U15*AB15) -> 0
AG16: =IF(U16="",1*AB16,U16*AB16) -> 0
AG17: =IF(U17="",1*AB17,U17*AB17) -> 0
AG18: =IF(U18="",1*AB18,U18*AB18) -> 0
AG19: =IF(U19="",1*AB19,U19*AB19) -> 0
AG20: =IF(U20="",1*AB20,U20*AB20) -> 0
AG21: =IF(U21="",1*AB21,U21*AB21) -> 0
AG22: =IF(U22="",1*AB22,U22*AB22) -> 0
AG23: =IF(U23="",1*AB23,U23*AB23) -> 0
AG24: =IF(U24="",1*AB24,U24*AB24) -> 0
... AG28: =IF(U28="",1*AB28,U28*AB28) -> 0
B29: FAX感熱紙(A4) | AG29: =IF(U29="",1*AB29,U29*AB29) -> 0
U30: 小 計 | AB30: =SUM(AG7:AG29) -> 76300
CS103: 単位
CS104: =見積書A4!CS104 -> 台
CS105: =見積書A4!CS105 -> 個
CS106: =見積書A4!CS106 -> 一式
CS107: =見積書A4!CS107 -> 冊
CS108: =見積書A4!CS108 -> 箱
CS109: =見積書A4!CS109 -> C/S
CS110: =見積書A4!CS110 -> SET
CS111: =見積書A4!CS111 -> 本
CS112: =見積書A4!CS112 -> 束
CS113: =見積書A4!CS113 -> 枚
CS114: =見積書A4!CS114 -> ﾊﾟｯｸ
CS115: =見積書A4!CS115 -> ｷｯﾄ
CS116: =見積書A4!CS116 -> 0
CI119: マスタパス | CM119: =見積書A4!CM119 -> C:\Documents and Settings\sato\My Documents\シンプル見積書\ | DO119: =見積書A4!$DO$119 -> マスタ 1.xls
CI120: データパス | CM120: =見積書A4!CM120 -> 0
P178: =見積書A4!P177 -> 0

Sheet USBフラッシュメモリ内一覧
D3: USBフラッシュメモリ内一覧 | AL3: No.
C5: 付 属 品 名 | U5: 数 量 | AB5: 単 価 | AG5: 金 額 | AN5: 備 考
C7: User Manual_FL_LCW-3000W Ver.2.0 （取扱 説明書) | U7: 1 | Y7: SET | AG7: =IF(U7="",1*AB7,U7*AB7) -> 0
C8: 焦点レンズの清掃・交換 | U8: 1 | Y8: SET | AG8: =IF(U8="",1*AB8,U8*AB8) -> 0
C9: 保護レンズの清掃・交換 | U9: 1 | Y9: SET
C10: 溶接の設定出し | U10: 1 | Y10: SET | AG10: =IF(U10="",1*AB10,U10*AB10) -> 0
C11: LCW全機種設定表 | U11: 1 | Y11: SET | AG11: =IF(U11="",1*AB11,U11*AB11) -> 0
C12: 3000W設定表 | U12: 1 | Y12: SET | AG12: =IF(U12="",1*AB12,U12*AB12) -> 0
AG13: =IF(U13="",1*AB13,U13*AB13) -> 0
AG14: =IF(U14="",1*AB14,U14*AB14) -> 0
AG15: =IF(U15="",1*AB15,U15*AB15) -> 0
AG16: =IF(U16="",1*AB16,U16*AB16) -> 0
AG17: =IF(U17="",1*AB17,U17*AB17) -> 0
AG18: =IF(U18="",1*AB18,U18*AB18) -> 0
AG19: =IF(U19="",1*AB19,U19*AB19) -> 0
AG20: =IF(U20="",1*AB20,U20*AB20) -> 0
AG21: =IF(U21="",1*AB21,U21*AB21) -> 0
AG22: =IF(U22="",1*AB22,U22*AB22) -> 0
AG23: =IF(U23="",1*AB23,U23*AB23) -> 0
AG24: =IF(U24="",1*AB24,U24*AB24) -> 0
... AG28: =IF(U28="",1*AB28,U28*AB28) -> 0
B29: FAX感熱紙(A4) | AG29: =IF(U29="",1*AB29,U29*AB29) -> 0
U30: 小 計
CS103: 単位
CS104: =見積書A4!CS104 -> 台
CS105: =見積書A4!CS105 -> 個
CS106: =見積書A4!CS106 -> 一式
CS107: =見積書A4!CS107 -> 冊
CS108: =見積書A4!CS108 -> 箱
CS109: =見積書A4!CS109 -> C/S
CS110: =見積書A4!CS110 -> SET
CS111: =見積書A4!CS111 -> 本
CS112: =見積書A4!CS112 -> 束
CS113: =見積書A4!CS113 -> 枚
CS114: =見積書A4!CS114 -> ﾊﾟｯｸ
CS115: =見積書A4!CS115 -> ｷｯﾄ
CS116: =見積書A4!CS116 -> 0
CI119: マスタパス | CM119: =見積書A4!CM119 -> C:\Documents and Settings\sato\My Documents\シンプル見積書\ | DO119: =見積書A4!$DO$119 -> マスタ 1.xls
CI120: データパス | CM120: =見積書A4!CM120 -> 0
P178: =見積書A4!P177 -> 0

Sheet 工具箱内付属一覧
D3: 工具箱内付属一覧 | AL3: No.
C5: 付 属 品 名 | U5: 数 量 | AB5: 単 価 | AG5: 金 額 | AN5: 備 考
C7: USBメモリー(取説・設定表・レンズ清掃方法 など) | U7: 1 | Y7: 一式 | AG7: =IF(U7="",1*AB7,U7*AB7) -> 0
C8: 溶接ノズル AS-12 | U8: 1 | Y8: 個 | AG8: =IF(U8="",1*AB8,U8*AB8) -> 0
C9: 溶接ノズル BS-16 | U9: 1 | Y9: 個 | AG9: =IF(U9="",1*AB9,U9*AB9) -> 0
C10: 溶接ノズル CS-12 | U10: 1 | Y10: 個 | AG10: =IF(U10="",1*AB10,U10*AB10) -> 0
C11: 溶接ノズル FS-16 | U11: 1 | Y11: 個 | AG11: =IF(U11="",1*AB11,U11*AB11) -> 0
C12: 溶接ノズル Ｃタイプ | U12: 1 | Y12: 個 | AG12: =IF(U12="",1*AB12,U12*AB12) -> 0
C13: 切断用ノズル | U13: 1 | Y13: 個 | AG13: =IF(U13="",1*AB13,U13*AB13) -> 0
C14: ワイヤーノズル Φ1.0 | U14: 1 | Y14: 個 | AG14: =IF(U14="",1*AB14,U14*AB14) -> 0
C15: ワイヤーノズル Φ1.2 | U15: 1 | Y15: 個 | AG15: =IF(U15="",1*AB15,U15*AB15) -> 0
C16: ワイヤーノズル Φ1.6 | U16: 1 | Y16: 個 | AG16: =IF(U16="",1*AB16,U16*AB16) -> 0
C17: レンズクリーナー | U17: 1 | Y17: 個 | AG17: =IF(U17="",1*AB17,U17*AB17) -> 0
C18: レンズクリーナー用拭き取り棒 | U18: 7 | Y18: 個 | AG18: =IF(U18="",1*AB18,U18*AB18) -> 0
... C28: レーザーケーブル保護キャップ | U28: 1 | Y28: 個 | AG28: =IF(U28="",1*AB28,U28*AB28) -> 0
B29: FAX感熱紙(A4) | AG29: =IF(U29="",1*AB29,U29*AB29) -> 0
U30: 小 計
CS103: 単位
CS104: =見積書A4!CS104 -> 台
CS105: =見積書A4!CS105 -> 個
CS106: =見積書A4!CS106 -> 一式
CS107: =見積書A4!CS107 -> 冊
CS108: =見積書A4!CS108 -> 箱
CS109: =見積書A4!CS109 -> C/S
CS110: =見積書A4!CS110 -> SET
CS111: =見積書A4!CS111 -> 本
CS112: =見積書A4!CS112 -> 束
CS113: =見積書A4!CS113 -> 枚
CS114: =見積書A4!CS114 -> ﾊﾟｯｸ
CS115: =見積書A4!CS115 -> ｷｯﾄ
CS116: =見積書A4!CS116 -> 0
CI119: マスタパス | CM119: =見積書A4!CM119 -> C:\Documents and Settings\sato\My Documents\シンプル見積書\ | DO119: =見積書A4!$DO$119 -> マスタ 1.xls
CI120: データパス | CM120: =見積書A4!CM120 -> 0
P178: =見積書A4!P177 -> 0

Sheet 本体装備品一覧
D3: 本体装備品一覧 | AL3: No.
C5: 付 属 品 名 | U5: 数 量 | AB5: 単 価 | AG5: 金 額 | AN5: 備 考
AB7: =SUM(Y19) -> 0 | AG7: =IF(U7="",1*AB7,U7*AB7) -> 0
AG8: =IF(U8="",1*AB8,U8*AB8) -> 0
AG9: =IF(U9="",1*AB9,U9*AB9) -> 0
AG10: =IF(U10="",1*AB10,U10*AB10) -> 0
AG11: =IF(U11="",1*AB11,U11*AB11) -> 0
AG12: =IF(U12="",1*AB12,U12*AB12) -> 0
AG13: =IF(U13="",1*AB13,U13*AB13) -> 0
AG14: =IF(U14="",1*AB14,U14*AB14) -> 0
AG15: =IF(U15="",1*AB15,U15*AB15) -> 0
AG16: =IF(U16="",1*AB16,U16*AB16) -> 0
AG17: =IF(U17="",1*AB17,U17*AB17) -> 0
AG18: =IF(U18="",1*AB18,U18*AB18) -> 0
AG19: =IF(U19="",1*AB19,U19*AB19) -> 0
... AG28: =IF(U28="",1*AB28,U28*AB28) -> 0
B29: FAX感熱紙(A4) | AG29: =IF(U29="",1*AB29,U29*AB29) -> 0
U30: 小 計
CS103: 単位
CS104: =見積書A4!CS104 -> 台
CS105: =見積書A4!CS105 -> 個
CS106: =見積書A4!CS106 -> 一式
CS107: =見積書A4!CS107 -> 冊
CS108: =見積書A4!CS108 -> 箱
CS109: =見積書A4!CS109 -> C/S
CS110: =見積書A4!CS110 -> SET
CS111: =見積書A4!CS111 -> 本
CS112: =見積書A4!CS112 -> 束
CS113: =見積書A4!CS113 -> 枚
CS114: =見積書A4!CS114 -> ﾊﾟｯｸ
CS115: =見積書A4!CS115 -> ｷｯﾄ
CS116: =見積書A4!CS116 -> 0
CI119: マスタパス | CM119: =見積書A4!CM119 -> C:\Documents and Settings\sato\My Documents\シンプル見積書\ | DO119: =見積書A4!$DO$119 -> マスタ 1.xls
CI120: データパス | CM120: =見積書A4!CM120 -> 0
P178: =見積書A4!P177 -> 0
