Workbook
Name if: 明細!$E$10

Sheet 入力
A1: 市町村名 | B1: 群馬県高崎市
A2: 案件名（自動生成に利用） | B2: デモ機操作・講習 見積書
A3: 宛先（会社名） | B3: 大塚刷毛製造株式会社 様
A4: 宛先（住所） | B4: 〒160-8511 東京都新宿区四谷4-1
A6: 見積番号 | B6: FL2511056
A7: 見積日 | B7: 45966
A8: 実施日(期日) | B8: 45990
A9: 実施場所 | B9: 群馬県高崎市内（会場未定）
A10: 支払条件 | B10: 末締め末現金払い
A11: 見積有効期限 | B11: 発行後30日
A12: 振込先（銀行名） | B12: 十六銀行 柳ヶ瀬支店
A13: 口座種別・番号 | B13: 普通 0777577
A14: 名義 | B14: カ)リンシュンドウ
A15: 登録番号（適格請求書） | B15: T6200001005823
A16: 発行元：会社名 | B16: 株式会社リンシュンドウ / サンマックスレーザー
A17: 発行元：住所 | B17: 〒502-0013 岐阜市中川原 サンマックスビル
A18: 発行元：メール | B18: MAIL:lasermachine.com@gmail.com
A19: 出発IC（例：岐阜 各IC） | B19: 岐阜 各IC
A20: 到着IC（マスタ連動） | B20: 高崎IC
A21: 片道ETC概算(円) | B21: 9700
A22: 往復ETC（自動計算） | B22: =B21*2 -> 19400
A23: 片道距離(km) | B23: 360
A24: 往復距離(km) | B24: =B23*2 -> 720
A25: 車両距離単価(円/km) | B25: 150
A26: 人数（日当・宿泊人数） | B26: 1
A27: 作業日数（日） | B27: 1
A28: 宿泊数（泊） | B28: 1
A29: 宿泊単価（円/泊・人） | B29: 10000
A30: 日当単価（円/日・人） | B30: 50000
A31: 窒素使用（あり/なし） | B31: あり
A32: 窒素単価（円/日） | B32: 5000

Sheet 明細
A1: 品名 | B1: 数量 | C1: 単位 | D1: 税別単価 | E1: 金額 | F1: 備考
A2: 出張デモ | B2: 1 | C2: 一式 | E2: =IF(B2="",1,B2)*D2 -> 0
A3: 交通費 往復（岐阜-高崎）社用車使用＠150 | B3: 1 | C3: 一式 | D3: =入力!B24*入力!B25 -> 108000 | E3: =IF(B3="",1,B3)*D3 -> 108000 | F3: 距離×単価（往復）／社用車使用
A4: 日当 1日1名分（平日） | B4: 1 | C4: 式 | D4: 50000 | E4: =IF(B4="",1,B4)*D4 -> 50000 | F4: 平日／人数×日数×日当単価
A5: 宿泊費（1泊2日×人数） | B5: 1 | C5: 式 | D5: =入力!B26*入力!B28*入力!B29 -> 10000 | E5: =IF(B5="",1,B5)*D5 -> 10000 | F5: 人数×泊数×宿泊単価（1泊）
A6: LCWデモ機展示設置費用（1.5kW相当） | B6: 1 | C6: 一式 | D6: 20000 | E6: =IF(B6="",1,B6)*D6 -> 20000 | F6: 設置費
A7: デモ用消耗品費 | B7: 1 | C7: 一式 | D7: 7500 | E7: =IF(B7="",1,B7)*D7 -> 7500 | F7: ワイヤ・試材・
A8: 窒素 | B8: 1 | C8: 日 | D8: 5000 | E8: =IF(B8="",1,B8)*D8 -> 5000 | F8: ="窒素使用（"&入力!B27&"日 × "&入力!B32&"円/日）" -> 窒素使用（1日 × 5000円/日）
A9: パーテーション | B9: 1 | C9: 一式 | D9: 5000 | E9: =IF(B9="",1,B9)*D9 -> 5000 | F9: 展示会やデモ会場用の簡易遮光パネル
A10: 保護メガネ 手袋 溶接台 | B10: 1 | C10: 一式 | D10: 5000 | E10: =IF(B10="",1,B10)*D10 -> 5000 | F10: デモ時に使用する専用作業台
A11: 値引き | C11: 一式 | D11: -10500 | E11: =IF(B11="",1,B11)*D11 -> -10500 | F11: ※値引き税別単価を負の金額

Sheet 見積書
A1: 御 見 積 書
D2: 見積番号 | E2: =入力!B6 -> FL2511056
A3: =入力!B3 -> 大塚刷毛製造株式会社 様 | D3: 見積日 | E3: =入力!B7 -> 45966
A4: =入力!B4 -> 〒160-8511 東京都新宿区四谷4-1
A7: =CONCATENATE(入力!B1," ",入力!B2,"（到着IC：",入力!B20,"）") -> 群馬県高崎市 デモ機操作・講習 見積書（到着IC：高崎IC）
A8: 支払条件 | B8: =入力!B10 -> 末締め末現金払い
A9: 見積有効期限 | B9: =入力!B11 -> 発行後30日
A10: 期日 | B10: =入力!B8 -> 45990
A11: 場所 | B11: =入力!B9 -> 群馬県高崎市内（会場未定）
A13: 品名 | B13: 数量 | C13: 単位 | D13: 税別単価 | E13: 金額 | F13: 備考
A14: =明細!A2 -> 出張デモ | B14: =明細!B2 -> 1 | C14: =明細!C2 -> 一式 | D14: =明細!D2 -> 0 | E14: =明細!E2 -> 0 | F14: =明細!F2 -> 0
A15: =明細!A3 -> 交通費 往復（岐阜-高崎）社用車使用＠150 | B15: =明細!B3 -> 1 | C15: =明細!C3 -> 一式 | D15: =明細!D3 -> 108000 | E15: =明細!E3 -> 108000 | F15: =明細!F3 -> 距離×単価（往復）／社用車使用
A16: =明細!A4 -> 日当 1日1名分（平日） | B16: =明細!B4 -> 1 | C16: =明細!C4 -> 式 | D16: =明細!D4 -> 50000 | E16: =明細!E4 -> 50000 | F16: =明細!F4 -> 平日／人数×日数×日当単価
A17: =明細!A5 -> 宿泊費（1泊2日×人数） | B17: =明細!B5 -> 1 | C17: =明細!C5 -> 式 | D17: =明細!D5 -> 10000 | E17: =明細!E5 -> 10000 | F17: =明細!F5 -> 人数×泊数×宿泊単価（1泊）
A18: =明細!A6 -> LCWデモ機展示設置費用（1.5kW相当） | B18: =明細!B6 -> 1 | C18: =明細!C6 -> 一式 | D18: =明細!D6 -> 20000 | E18: =明細!E6 -> 20000 | F18: =明細!F6 -> 設置費
A19: =明細!A7 -> デモ用消耗品費 | B19: =明細!B7 -> 1 | C19: =明細!C7 -> 一式 | D19: =明細!D7 -> 7500 | E19: =明細!E7 -> 7500 | F19: =明細!F7 -> ワイヤ・試材・
A20: =明細!A8 -> 窒素 | B20: =明細!B8 -> 1 | C20: =明細!C8 -> 日 | D20: =明細!D8 -> 5000 | E20: =明細!E8 -> 5000 | F20: =明細!F8 -> 窒素使用（1日 × 5000円/日）
A21: =明細!A9 -> パーテーション | B21: =明細!B9 -> 1 | C21: =明細!C9 -> 一式 | D21: =明細!D9 -> 5000 | E21: =明細!E9 -> 5000 | F21: =明細!F9 -> 展示会やデモ会場用の簡易遮光パネル
A22: =明細!A10 -> 保護メガネ 手袋 溶接台 | B22: =明細!B10 -> 1 | C22: =明細!C10 -> 一式 | D22: =明細!D10 -> 5000 | E22: =明細!E10 -> 5000 | F22: =明細!F10 -> デモ時に使用する専用作業台
B23: =明細!B11 -> 0 | C23: =明細!C11 -> 一式
D24: 小計 | E24: =SUM(E14:E23) -> 210500
D25: 消費税(10%) | E25: =ROUND(E24*0.1,0) -> 21050
D26: 税込合計 | E26: =E24+E25 -> 231550
A28: 摘要（注意事項） | B28: デモ機の搬入・撤収時は男性のお手伝いを要します。 電源御社手配をお願いします。 ※交通費等は自動計算に基づく概算です。実費精算時に差額調整する場合があります。
A33: 振込先 | B33: =入力!B12 -> 十六銀行 柳ヶ瀬支店 | D33: 登録番号 | E33: =入力!B15 -> T6200001005823
A34: 口座 | B34: =入力!B13 -> 普通 0777577
A35: 名義 | B35: =入力!B14 -> カ)リンシュンドウ
A37: 発行元 | B37: =入力!B16 -> 株式会社リンシュンドウ / サンマックスレーザー
A38: 所在地 | B38: =入力!B17 -> 〒502-0013 岐阜市中川原 サンマックスビル
A39: 連絡先 | B39: =入力!B18 -> MAIL:lasermachine.com@gmail.com

Sheet 納品書
A1: 納 品 書
D2: 見積番号 | E2: =入力!B6 -> FL2511056
A3: =入力!B3 -> 大塚刷毛製造株式会社 様 | D3: 見積日 | E3: =入力!B7 -> 45966
A4: =入力!B4 -> 〒160-8511 東京都新宿区四谷4-1
A7: =CONCATENATE(入力!B1," ",入力!B2,"（到着IC：",入力!B20,"）") -> 群馬県高崎市 デモ機操作・講習 見積書（到着IC：高崎IC）
A8: 支払条件 | B8: =入力!B10 -> 末締め末現金払い
A9: 見積有効期限 | B9: =入力!B11 -> 発行後30日
A10: 期日 | B10: =入力!B8 -> 45990
A11: 場所 | B11: =入力!B9 -> 群馬県高崎市内（会場未定）
A13: 品名 | B13: 数量 | C13: 単位 | D13: 税別単価 | E13: 金額 | F13: 備考
A14: =明細!A2 -> 出張デモ | B14: =明細!B2 -> 1 | C14: =明細!C2 -> 一式 | D14: =明細!D2 -> 0 | E14: =明細!E2 -> 0 | F14: =明細!F2 -> 0
A15: =明細!A3 -> 交通費 往復（岐阜-高崎）社用車使用＠150 | B15: =明細!B3 -> 1 | C15: =明細!C3 -> 一式 | F15: =明細!F3 -> 距離×単価（往復）／社用車使用
A16: =明細!A4 -> 日当 1日1名分（平日） | B16: =明細!B4 -> 1 | C16: =明細!C4 -> 式 | F16: =明細!F4 -> 平日／人数×日数×日当単価
A17: =明細!A5 -> 宿泊費（1泊2日×人数） | B17: =明細!B5 -> 1 | C17: =明細!C5 -> 式 | F17: =明細!F5 -> 人数×泊数×宿泊単価（1泊）
A18: =明細!A6 -> LCWデモ機展示設置費用（1.5kW相当） | B18: =明細!B6 -> 1 | C18: =明細!C6 -> 一式 | F18: =明細!F6 -> 設置費
A19: =明細!A7 -> デモ用消耗品費 | B19: =明細!B7 -> 1 | C19: =明細!C7 -> 一式 | F19: =明細!F7 -> ワイヤ・試材・
A20: =明細!A8 -> 窒素 | B20: =明細!B8 -> 1 | C20: =明細!C8 -> 日 | F20: =明細!F8 -> 窒素使用（1日 × 5000円/日）
A21: =明細!A9 -> パーテーション | B21: =明細!B9 -> 1 | C21: =明細!C9 -> 一式 | F21: =明細!F9 -> 展示会やデモ会場用の簡易遮光パネル
A22: =明細!A10 -> 保護メガネ 手袋 溶接台 | B22: =明細!B10 -> 1 | C22: =明細!C10 -> 一式 | F22: =明細!F10 -> デモ時に使用する専用作業台
B23: =明細!B11 -> 0 | C23: =明細!C11 -> 一式
D24: 小計
D25: 消費税(10%)
D26: 税込合計
A28: 摘要（注意事項） | B28: デモ機の搬入・撤収時は男性のお手伝いを要します。 電源御社手配をお願いします。 ※交通費等は自動計算に基づく概算です。実費精算時に差額調整する場合があります。
A33: 振込先 | B33: =入力!B12 -> 十六銀行 柳ヶ瀬支店 | D33: 登録番号 | E33: =入力!B15 -> T6200001005823
A34: 口座 | B34: =入力!B13 -> 普通 0777577
A35: 名義 | B35: =入力!B14 -> カ)リンシュンドウ
A37: 発行元 | B37: =入力!B16 -> 株式会社リンシュンドウ / サンマックスレーザー
A38: 所在地 | B38: =入力!B17 -> 〒502-0013 岐阜市中川原 サンマックスビル
A39: 連絡先 | B39: =入力!B18 -> MAIL:lasermachine.com@gmail.com
